{
 "source": "ధూర్తమానవా శతకము",
 "count": 36,
 "poems": [
  {
   "id": 2521,
   "title": "ధూర్తమానవా శతకము - 1",
   "text": "ఏఁ బదునాల్గులోకముల-సృష్టియొనర్చుచుఁ బెంచి పిమ్మటన్‌\nదూబవలెన్‌ హరింతు నని-దొంగనుడుల్‌ వచియించు చుంటివే!\nయేఁబదిమాట లేమిటికి?-ఇట్టి ప్రచారము మానకున్నచో\nగూబలు సాఁగఁదీసెదను-గూయకు మిట్టివి ధూర్తమానవా!",
   "literary_form": "శతకం",
   "source": "ధూర్తమానవా శతకము",
   "kanda": null,
   "flags": null,
   "rating": "gold",
   "prathipadartham": [
    {
     "word": "ఏఁ",
     "meaning": "నేను"
    },
    {
     "word": "బదునాల్గులోకముల",
     "meaning": "పదునాల్గు భువనాలను"
    },
    {
     "word": "సృష్టియొనర్చుచున్‌",
     "meaning": "సృష్టిస్తూ"
    },
    {
     "word": "పెంచి",
     "meaning": "పోషిస్తూ"
    },
    {
     "word": "పిమ్మటన్‌",
     "meaning": "తరువాత"
    },
    {
     "word": "దూబవలెన్‌",
     "meaning": "గడ్డిపోచ వలె"
    },
    {
     "word": "హరింతును",
     "meaning": "నాశనం చేస్తాను"
    },
    {
     "word": "అని",
     "meaning": "అని"
    },
    {
     "word": "దొంగనుడుల్‌",
     "meaning": "అబద్ధపు మాటలను"
    },
    {
     "word": "వచియించుచుంటివే",
     "meaning": "పలుకుతున్నావా"
    },
    {
     "word": "యేఁబదిమాటలేమిటికి",
     "meaning": "ఎక్కువ మాటలు ఎందుకు"
    },
    {
     "word": "ఇట్టి ప్రచారము",
     "meaning": "ఇలాంటి అసత్య ప్రచారాన్ని"
    },
    {
     "word": "మానకున్నచో",
     "meaning": "మానుకోకపోతే"
    },
    {
     "word": "గూబలు",
     "meaning": "కళ్లు (మెడలు)"
    },
    {
     "word": "సాఁగఁదీసెదను",
     "meaning": "లాగి పీకేస్తాను"
    },
    {
     "word": "గూయకుమిట్టివి",
     "meaning": "ఇలాంటివి మాట్లాడకు"
    },
    {
     "word": "ధూర్తమానవా",
     "meaning": "ఓ దుర్మార్గుడా"
    }
   ],
   "bhavam": "ఓ ధూర్తుడా! 'నేనే పదునాల్గు లోకాలను సృష్టించి, పోషించి, చివరకు గడ్డిపోచలా నాశనం చేస్తాను' అని ఎందుకు అబద్ధాలు పలుకుతున్నావు? వృథా మాటలు కట్టిపెట్టు. ఇలాంటి మూర్ఖపు ప్రచారాలు మానకపోతే నీ మెడలు పట్టుకుని లాగి పీకేస్తాను, ఇకనైనా నోరు మూసుకో.",
   "word_count": 17,
   "gana_count": null,
   "line_count": 4,
   "poet_id": 23,
   "poet_name": "త్రిపురనేని రామస్వామి",
   "meter_id": 8,
   "meter_name": "ఉత్పలమాల"
  },
  {
   "id": 2522,
   "title": "ధూర్తమానవా శతకము - 2",
   "text": "ఎవ్వరు చూచినారు సృజి-యింపఁగ నీ పదునాల్గులోకముల్‌\nసువ్వన సువ్వి సువ్వి యను-చొప్పెకదా! యొకఁడైనఁ జూచెనే\nదవ్వులనుండియైన నొక-దానినినైన? వృథా ప్రగల్భముల్‌!\nనవ్వుల పాలుఁజేసెదవె-నన్నిటులాడుచు ధూర్తమానవా!",
   "literary_form": "శతకం",
   "source": "ధూర్తమానవా శతకము",
   "kanda": null,
   "flags": null,
   "rating": "gold",
   "prathipadartham": [
    {
     "word": "ఎవ్వరు",
     "meaning": "ఏ మానవుడు"
    },
    {
     "word": "చూచినారు",
     "meaning": "చూశారు"
    },
    {
     "word": "సృజియింపఁగ",
     "meaning": "సృష్టించేటప్పుడు"
    },
    {
     "word": "నీ",
     "meaning": "నీవు చెబుతున్న"
    },
    {
     "word": "పదునాల్గు",
     "meaning": "పదునాలుగు"
    },
    {
     "word": "లోకముల్‌",
     "meaning": "లోకాలను"
    },
    {
     "word": "సువ్వన",
     "meaning": "సువ్వి సువ్వి అని పాట పాడుతూ"
    },
    {
     "word": "సువ్వి",
     "meaning": "సువ్వి"
    },
    {
     "word": "సువ్వి",
     "meaning": "సువ్వి"
    },
    {
     "word": "అనుచొప్పెకదా",
     "meaning": "అనే పద్ధతి కదా (అసత్యం)"
    },
    {
     "word": "ఒకఁడైనఁ",
     "meaning": "కనీసం ఒక్కడైనా"
    },
    {
     "word": "చూచెనే",
     "meaning": "చూశాడా"
    },
    {
     "word": "దవ్వులనుండియైన",
     "meaning": "దూరం నుండి అయినా"
    },
    {
     "word": "ఒకదానినినైన",
     "meaning": "ఒక్క లోకాన్నైనా"
    },
    {
     "word": "వృథా",
     "meaning": "వ్యర్థమైన"
    },
    {
     "word": "ప్రగల్భముల్‌",
     "meaning": "గొప్పలు"
    },
    {
     "word": "నవ్వుల",
     "meaning": "నవ్వుల పాలు"
    },
    {
     "word": "పాలుఁజేసెదవె",
     "meaning": "చేస్తున్నావా"
    },
    {
     "word": "నన్నిటు",
     "meaning": "నన్ను ఇలా"
    },
    {
     "word": "ఆడుచు",
     "meaning": "అంటూ ఆటపట్టిస్తూ"
    },
    {
     "word": "ధూర్తమానవా",
     "meaning": "ఓ ధూర్త మానవుడా"
    }
   ],
   "bhavam": "ఓ ధూర్త మానవుడా! ఈ పదునాలుగు లోకాలను సృష్టించేటప్పుడు ఎవరైనా చూశారా? సువ్వి సువ్వి అంటూ పాడుకుంటూ సృష్టించాడని చెప్పడం కేవలం ఒక కల్పిత కథ మాత్రమే. కనీసం ఒక్కడైనా సరే, దూరంగా ఉండి కూడా ఆ సృష్టిని ఎప్పుడైనా చూశారా? ఇలాంటి వ్యర్థమైన మాటలు చెప్పి నన్ను నవ్వుల పాలు చేయకు.",
   "word_count": 18,
   "gana_count": null,
   "line_count": 4,
   "poet_id": 23,
   "poet_name": "త్రిపురనేని రామస్వామి",
   "meter_id": 8,
   "meter_name": "ఉత్పలమాల"
  },
  {
   "id": 2523,
   "title": "ధూర్తమానవా శతకము - 3",
   "text": "ప్రతివర్షంబును నా వివాహ మను పే-రన్‌ బెక్కుచందాల దు\nర్మతి చందాలు వసూలుచేసి ప్రతియూ-రన్‌ గజ్జకట్టింతువే!\nగతి యీమాత్రములేదె నాకరయ? నేఁ-గావించుకోలేనె? యీ\nగతి నన్నీవు పరాభవించుటకు సం-కల్పింతువే మానవా!",
   "literary_form": "శతకం",
   "source": "ధూర్తమానవా శతకము",
   "kanda": null,
   "flags": null,
   "rating": "gold",
   "prathipadartham": [
    {
     "word": "ప్రతివర్షంబును",
     "meaning": "ప్రతి ఏటా"
    },
    {
     "word": "నా వివాహము అను పేరున",
     "meaning": "నా పెళ్లి పేరుతో"
    },
    {
     "word": "పెక్కుచందాల",
     "meaning": "అనేక రకాలుగా"
    },
    {
     "word": "దుర్మతి",
     "meaning": "దుష్టబుద్ధి కలవాడా"
    },
    {
     "word": "చందాలు వసూలుచేసి",
     "meaning": "చందాలు అడిగి తీసుకుని"
    },
    {
     "word": "ప్రతి ఊరన్",
     "meaning": "ప్రతి గ్రామంలోనూ"
    },
    {
     "word": "గజ్జకట్టింతువే",
     "meaning": "నన్ను గజ్జెలు కట్టి ఆడిస్తున్నావా"
    },
    {
     "word": "గతి",
     "meaning": "దారి / శక్తి"
    },
    {
     "word": "ఈమాత్రము లేదె",
     "meaning": "కొంచెం కూడా లేదా"
    },
    {
     "word": "నాకు",
     "meaning": "నాకు"
    },
    {
     "word": "అరయ",
     "meaning": "ఆలోచిస్తే"
    },
    {
     "word": "నేన్",
     "meaning": "నేను"
    },
    {
     "word": "కావించుకోలేనె",
     "meaning": "చేసుకోలేనా"
    },
    {
     "word": "ఈ గతిన్",
     "meaning": "ఈ విధంగా"
    },
    {
     "word": "అన్ను",
     "meaning": "నన్ను"
    },
    {
     "word": "ఈవు",
     "meaning": "నీవు"
    },
    {
     "word": "పరాభవించుటకు",
     "meaning": "అవమానించడానికి"
    },
    {
     "word": "సంకల్పింతువే",
     "meaning": "నిశ్చయించుకున్నావా"
    },
    {
     "word": "మానవా",
     "meaning": "ఓ మనిషి"
    }
   ],
   "bhavam": "ఓ మనిషీ! నా పెళ్లి పేరు చెప్పి, ప్రతి ఏటా నీ దుష్టబుద్ధితో ఊరూరూ తిరిగి చందాలు వసూలు చేస్తూ, నన్ను గజ్జెలు కట్టి నాట్యం చేయిస్తున్నావా? అసలు నాకంటూ ఏ గతి లేదా? నేనే సొంతంగా పెళ్లి చేసుకోలేనా? ఇలా నన్ను నిరంతరం అవమానించాలని ఎందుకు కంకణం కట్టుకున్నావు?",
   "word_count": 22,
   "gana_count": null,
   "line_count": 4,
   "poet_id": 23,
   "poet_name": "త్రిపురనేని రామస్వామి",
   "meter_id": 7,
   "meter_name": "మత్తేభవిక్రీడితము"
  },
  {
   "id": 2524,
   "title": "ధూర్తమానవా శతకము - 4",
   "text": "కాపురముండ నిల్లు, నడ-కత్తెరలోఁ బడియుండఁ బెండ్లమున్‌,\nమాపులు కున్కఁగాఁ బడక-మంచము, నెక్కగ నెక్కిరింతలున్‌,\nసాపడఁ బైడికంచమును-జక్కగఁగూర్చి యుపన్యసింతువే?\nనీపనిఁ బట్టెదన్‌ వినుము-నీవిది మానవ ధూర్తమానవా!",
   "literary_form": "శతకం",
   "source": "ధూర్తమానవా శతకము",
   "kanda": null,
   "flags": null,
   "rating": "gold",
   "prathipadartham": [
    {
     "word": "కాపురముండ",
     "meaning": "నివసించడానికి"
    },
    {
     "word": "ఇల్లు",
     "meaning": "నివాస గృహం"
    },
    {
     "word": "నడకత్తెరలో",
     "meaning": "అడకత్తెర వంటి ఇబ్బందుల్లో"
    },
    {
     "word": "బడియుండ",
     "meaning": "చిక్కుకొని ఉన్న"
    },
    {
     "word": "పెండ్లమున్‌",
     "meaning": "భార్యను"
    },
    {
     "word": "మాపులు",
     "meaning": "సాయంత్రాలు"
    },
    {
     "word": "కున్కఁగాఁ",
     "meaning": "పడుకోగా/నిద్రపోగా"
    },
    {
     "word": "బడకమంచము",
     "meaning": "నిద్రించడానికి మంచం"
    },
    {
     "word": "నెక్కగ",
     "meaning": "ఎక్కడానికి"
    },
    {
     "word": "నెక్కిరింతలున్‌",
     "meaning": "ఎగతాళి చేసే నవ్వులు"
    },
    {
     "word": "సాపడ",
     "meaning": "భుజించడానికి"
    },
    {
     "word": "బైడికంచమును",
     "meaning": "బంగారు పళ్లెమును"
    },
    {
     "word": "జక్కగఁగూర్చి",
     "meaning": "అందంగా అమర్చుకొని"
    },
    {
     "word": "ఉపన్యసింతువే",
     "meaning": "ఉపన్యాసాలు ఇస్తావా"
    },
    {
     "word": "నీపని",
     "meaning": "నీ బండారాన్ని"
    },
    {
     "word": "పట్టెదన్‌",
     "meaning": "బయటపెడతాను/పట్టుకుంటాను"
    },
    {
     "word": "వినుము",
     "meaning": "వినవయ్యా"
    },
    {
     "word": "నీవిది",
     "meaning": "నీవు చేస్తున్న ఈ పనిని"
    },
    {
     "word": "మానవ",
     "meaning": "ఓ మనిషీ"
    },
    {
     "word": "ధూర్తమానవా",
     "meaning": "ఓ ధూర్తుడా (మోసగాడా)"
    }
   ],
   "bhavam": "ఓ ధూర్తుడా! నీవు నివసించడానికి ఒక ఇల్లు, అడకత్తెరలో పడ్డట్టున్న పరిస్థితుల్లో ఉన్న భార్య, పడుకోవడానికి మంచం, ఎక్కడానికి నవ్వులు, తినడానికి బంగారు పళ్లెం వంటి సౌకర్యాలను అమర్చుకొని, గొప్ప గొప్ప ఉపన్యాసాలు ఇస్తావా? నీ అసలు స్వరూపాన్ని, నీ బండారాన్ని నేను బయటపెడతాను విను.",
   "word_count": 18,
   "gana_count": null,
   "line_count": 4,
   "poet_id": 23,
   "poet_name": "త్రిపురనేని రామస్వామి",
   "meter_id": 8,
   "meter_name": "ఉత్పలమాల"
  },
  {
   "id": 2525,
   "title": "ధూర్తమానవా శతకము - 5",
   "text": "కొస కేమౌనొ యెఱుంగకుండ నుసితోఁ-గోణంగివై నీవు నీ\nపుసికన్నుల్‌ మసిముక్కు దేబెమొగమున్‌-బువ్వాడు పెన్‌బోరెమున్‌\nతొసినోరున్‌ గలిగించి వంచకుఁడవై-దుర్జాతి, నన్నొక్క మా\nనిసినిం జేసెదవే! మనుష్యునివలెన్‌-నేనుంటినే మానవా!",
   "literary_form": "శతకం",
   "source": "ధూర్తమానవా శతకము",
   "kanda": null,
   "flags": null,
   "rating": "gold",
   "prathipadartham": [
    {
     "word": "కొస",
     "meaning": "చివరికి (పరిణామం)"
    },
    {
     "word": "ఏమౌనొ",
     "meaning": "ఏమవుతుందో"
    },
    {
     "word": "ఎఱుంగకుండ",
     "meaning": "తెలియకుండా"
    },
    {
     "word": "ఉసితోన్",
     "meaning": "ఆశతో (తుంటరితనంతో)"
    },
    {
     "word": "కోణంగివై",
     "meaning": "కోతి చేష్టలు చేసేవాడివై (వికృత రూపంతో)"
    },
    {
     "word": "నీవు",
     "meaning": "నీవు"
    },
    {
     "word": "నీ",
     "meaning": "నీ యొక్క"
    },
    {
     "word": "పుసికన్నుల్",
     "meaning": "జిగటతో కూడిన కళ్లు"
    },
    {
     "word": "మసిముక్కు",
     "meaning": "నల్లని ముక్కు"
    },
    {
     "word": "దేబెమొగమున్",
     "meaning": "వికృతమైన ముఖం"
    },
    {
     "word": "బువ్వాడు",
     "meaning": "అన్నం తినే (మురికిగా ఉండే)"
    },
    {
     "word": "పెన్‌బోరెమున్",
     "meaning": "పెద్ద వికృత దేహం"
    },
    {
     "word": "తొసినోరున్",
     "meaning": "ఊడిన పళ్లుగల నోరు"
    },
    {
     "word": "కలిగించి",
     "meaning": "కల్పించుకొని"
    },
    {
     "word": "వంచకుఁడవై",
     "meaning": "మోసగాడివై"
    },
    {
     "word": "దుర్జాతి",
     "meaning": "నీచమైన జాతికి చెందినవాడా"
    },
    {
     "word": "నన్ను",
     "meaning": "నన్ను"
    },
    {
     "word": "ఒక్క",
     "meaning": "ఒక"
    },
    {
     "word": "మానిసినిన్",
     "meaning": "మనిషినిగా"
    },
    {
     "word": "చేసెదవే",
     "meaning": "చేస్తున్నావా"
    },
    {
     "word": "మనుష్యునివలెన్",
     "meaning": "మనుష్యునిలాగా"
    },
    {
     "word": "నేనుంటినే",
     "meaning": "నేను ఉన్నానా"
    },
    {
     "word": "మానవా",
     "meaning": "ఓ మనిషీ"
    }
   ],
   "bhavam": "ఓ మనిషీ! నీవు చివరికి ఏమవుతుందో కూడా తెలియక, కోతి చేష్టలతో వికృతమైన కళ్లు, మసిముక్కు, వికృతమైన ముఖం, మురికి దేహం, ఊడిన పళ్లు ఉన్న నోరు కలిగి ఉండి, మోసగాడివై నన్ను మనిషిని అని పిలుస్తున్నావా? అసలు నేను నీలాంటి మనుష్యుడిలా ఉన్నానా? (నీ వికృత ప్రవర్తన వల్ల నేను మనిషిగా అనిపించడం లేదు అని తాత్పర్యం).",
   "word_count": 19,
   "gana_count": null,
   "line_count": 4,
   "poet_id": 23,
   "poet_name": "త్రిపురనేని రామస్వామి",
   "meter_id": 7,
   "meter_name": "మత్తేభవిక్రీడితము"
  },
  {
   "id": 2526,
   "title": "ధూర్తమానవా శతకము - 6",
   "text": "కాలుంజేతులు ముక్కు మోములును చం-కల్‌ చన్నులున్‌ బేర్లు నీ\nకేలా యున్నవొ; నాకు నట్లెకలవా?-యీరీతిగా నన్ను నీ\nవేలా వర్ణనచేసినాడ వకటా!-యెందాక సైరింతు? నిన్‌\nపాలార్తున్‌ మునుమున్న చెప్పితిని నీ-పాట్లన్నియున్‌ మానవా!",
   "literary_form": "శతకం",
   "source": "ధూర్తమానవా శతకము",
   "kanda": null,
   "flags": null,
   "rating": "gold",
   "prathipadartham": [
    {
     "word": "కాలుంజేతులు",
     "meaning": "కాళ్లు మరియు చేతులు"
    },
    {
     "word": "ముక్కు",
     "meaning": "నాసిక"
    },
    {
     "word": "మోములును",
     "meaning": "ముఖములు కూడా"
    },
    {
     "word": "చంకల్",
     "meaning": "చంకలు"
    },
    {
     "word": "చన్నులున్‌",
     "meaning": "స్తనాలు కూడా"
    },
    {
     "word": "బేర్లు",
     "meaning": "పేర్లు"
    },
    {
     "word": "నీకేలా యున్నవొ",
     "meaning": "నీకు ఏ విధంగా ఉన్నాయో"
    },
    {
     "word": "నాకు నట్లెకలవా?",
     "meaning": "నాకు కూడా అలాగే లేవా?"
    },
    {
     "word": "ఈ రీతిగా",
     "meaning": "ఈ పద్ధతిలో"
    },
    {
     "word": "నన్ను నీవేలా",
     "meaning": "నన్ను నీవు ఎందుకు"
    },
    {
     "word": "వర్ణనచేసినాడ",
     "meaning": "వర్ణిస్తున్నావు"
    },
    {
     "word": "వకటా!",
     "meaning": "అయ్యో!"
    },
    {
     "word": "యెందాక సైరింతు?",
     "meaning": "ఎంతవరకు సహిస్తాను?"
    },
    {
     "word": "నిన్‌",
     "meaning": "నిన్ను"
    },
    {
     "word": "పాలార్తున్‌",
     "meaning": "నాశనం చేస్తాను"
    },
    {
     "word": "మునుమున్న చెప్పితిని",
     "meaning": "ముందే చెప్పాను"
    },
    {
     "word": "నీ పాట్లన్నియున్‌",
     "meaning": "నీ కష్టాలన్నింటిని"
    },
    {
     "word": "మానవా!",
     "meaning": "ఓ మనిషీ!"
    }
   ],
   "bhavam": "ఓ మనిషీ! నీకు ఉన్న కాళ్లు, చేతులు, ముక్కు, ముఖం, చంకలు, చన్నులు, పేర్లు నాకు కూడా అలాగే ఉన్నాయి కదా! మరి అలాంటప్పుడు నన్ను ఈ విధంగా ఎందుకు వర్ణిస్తున్నావు? నీవు చేసే ఈ పనులను నేను ఎంతవరకు సహిస్తాను? ఇలాగే కొనసాగిస్తే నిన్ను నాశనం చేస్తాను, జాగ్రత్త అని నీకు ముందే చెబుతున్నాను.",
   "word_count": 23,
   "gana_count": null,
   "line_count": 4,
   "poet_id": 23,
   "poet_name": "త్రిపురనేని రామస్వామి",
   "meter_id": 6,
   "meter_name": "శార్దూలవిక్రీడితము"
  },
  {
   "id": 2527,
   "title": "ధూర్తమానవా శతకము - 7",
   "text": "గుడులున్‌ గోపురముల్‌ కుశీలవుఁడవై-కూర్పించి చందాలతో\nమడిమాన్యంబులు నాదు పేరుననె ని-ర్మాణంబు గావించుచున్‌\nవడపప్పున్‌ బెరవారి కిచ్చెదవె? నీ-భావంబునం దేమి గీ\nల్పడఁగా నేర్చెడి? చెప్పు మింతటి దివా-లాఖోరువే మానవా!",
   "literary_form": "శతకం",
   "source": "ధూర్తమానవా శతకము",
   "kanda": null,
   "flags": null,
   "rating": "gold",
   "prathipadartham": [
    {
     "word": "గుడులున్",
     "meaning": "దేవాలయములను"
    },
    {
     "word": "గోపురముల్",
     "meaning": "గోపురములను"
    },
    {
     "word": "కుశీలవుడవై",
     "meaning": "నటుడవై/వేషధారివై"
    },
    {
     "word": "కూర్పించి",
     "meaning": "నిర్మించి"
    },
    {
     "word": "చందాలతో",
     "meaning": "విధములతో/విధానములతో"
    },
    {
     "word": "మడిమాన్యంబులు",
     "meaning": "భూములను"
    },
    {
     "word": "నాదు",
     "meaning": "నా"
    },
    {
     "word": "పేరుననె",
     "meaning": "పేరుమీదనే"
    },
    {
     "word": "నిర్మాణంబు",
     "meaning": "ఏర్పాటు"
    },
    {
     "word": "గావించుచున్",
     "meaning": "చేయుచు"
    },
    {
     "word": "వడపప్పున్",
     "meaning": "వడపప్పును"
    },
    {
     "word": "బెరవారికి",
     "meaning": "ఇతరులకు/చుట్టుపక్కల వారికి"
    },
    {
     "word": "ఇచ్చెదవె",
     "meaning": "దానము చేస్తున్నావా"
    },
    {
     "word": "నీ",
     "meaning": "నీ"
    },
    {
     "word": "భావంబునందు",
     "meaning": "మనస్సులో"
    },
    {
     "word": "ఏమి",
     "meaning": "ఏ"
    },
    {
     "word": "గీల్పడగా",
     "meaning": "మాయ/కుతంత్రం"
    },
    {
     "word": "నేర్చెడి",
     "meaning": "నేర్చుకున్నావు"
    },
    {
     "word": "చెప్పుము",
     "meaning": "చెప్పు"
    },
    {
     "word": "ఇంతటి",
     "meaning": "ఇంతటి"
    },
    {
     "word": "దివాలాఖోరువే",
     "meaning": "దివాలా తీసినవాడివా/మోసగాడివా"
    },
    {
     "word": "మానవా",
     "meaning": "ఓ మనిషీ"
    }
   ],
   "bhavam": "ఓ మనిషీ! నటుని వలె వేషాలు వేస్తూ గుడులను, గోపురాలను నిర్మిస్తున్నావు. నా పేరు మీదనే భూములను దానం చేస్తున్నట్లుగా గొప్పగా చెప్పుకుంటూ, అసలు నీ స్వార్థం కోసం వడపప్పును ఇతరులకు పంచుతున్నావా? నీ మనసులో ఏ కుతంత్రం దాగుందో చెప్పు? ఇంతటి దివాలాఖోరుతనమా నీది?",
   "word_count": 21,
   "gana_count": null,
   "line_count": 4,
   "poet_id": 23,
   "poet_name": "త్రిపురనేని రామస్వామి",
   "meter_id": 7,
   "meter_name": "మత్తేభవిక్రీడితము"
  },
  {
   "id": 2528,
   "title": "ధూర్తమానవా శతకము - 8",
   "text": "వేదము లెట్లు బ్రహ్మముఖ-వీథులనుండి హరింపఁగాఁ బడున్‌;\nపాదలి సోమకాసురుఁడు-వచ్చి త్రయిన్‌ హరియించె నంచు నే\nచీదరఁ బొందకుండ చొఱ-చేఁపను జేసితివే ననున్‌ - సరే!\nనీదయమీద నా బ్రదుకు-నిల్చెనె చెప్పుమ ధూర్తమానవా!",
   "literary_form": "శతకం",
   "source": "ధూర్తమానవా శతకము",
   "kanda": null,
   "flags": null,
   "rating": "gold",
   "prathipadartham": [
    {
     "word": "వేదములు",
     "meaning": "వేదాలను"
    },
    {
     "word": "ఎట్లు",
     "meaning": "ఏ విధంగా"
    },
    {
     "word": "బ్రహ్మముఖ-వీథులనుండి",
     "meaning": "బ్రహ్మదేవుని నోటి నుండి"
    },
    {
     "word": "హరింపఁగాఁ బడున్‌",
     "meaning": "దొంగిలించబడ్డాయో"
    },
    {
     "word": "పాదలి",
     "meaning": "దుర్మార్గుడైన"
    },
    {
     "word": "సోమకాసురుఁడు",
     "meaning": "సోమకాసురుడు అనే రాక్షసుడు"
    },
    {
     "word": "వచ్చి",
     "meaning": "వచ్చి"
    },
    {
     "word": "త్రయిన్‌",
     "meaning": "మూడు వేదాలను"
    },
    {
     "word": "హరియించె",
     "meaning": "అపహరించాడు"
    },
    {
     "word": "అంచు",
     "meaning": "అని"
    },
    {
     "word": "ఏ",
     "meaning": "ఎంతటి"
    },
    {
     "word": "చీదరఁ",
     "meaning": "అసహ్యాన్ని"
    },
    {
     "word": "పొందకుండ",
     "meaning": "పొందకుండా"
    },
    {
     "word": "చొఱ-చేఁపను",
     "meaning": "మత్స్యరూపాన్ని (చేప రూపాన్ని)"
    },
    {
     "word": "జేసితివే",
     "meaning": "ధరించావు కదా"
    },
    {
     "word": "ననున్‌",
     "meaning": "నన్ను"
    },
    {
     "word": "సరే",
     "meaning": "సరే"
    },
    {
     "word": "నీదయమీద",
     "meaning": "నీ కరుణ మీదనే"
    },
    {
     "word": "నా బ్రదుకు",
     "meaning": "నా జీవనం"
    },
    {
     "word": "నిల్చెనె",
     "meaning": "నిలిచి ఉందా"
    },
    {
     "word": "చెప్పుమ",
     "meaning": "చెప్పు"
    },
    {
     "word": "ధూర్తమానవా",
     "meaning": "ఓ ధూర్తమానవా (మోసపూరిత మనిషి/దేవుడా)"
    }
   ],
   "bhavam": "ఓ ధూర్తమానవా! పూర్వం సోమకాసురుడు బ్రహ్మ నోటి నుండి వేదాలను దొంగిలించినప్పుడు, ఆ వేదాలను రక్షించడానికి నీవు అసహ్యించుకోకుండా మత్స్యరూపాన్ని ధరించి కాపాడావు కదా! అలాగే నీవు నా మీద దయ చూపి నా బ్రతుకును నిలబెట్టావని అనుకోవాలా? అసలు నీ కృప వల్లే నా జీవితం నడుస్తుందా? నిజమేదో చెప్పు.",
   "word_count": 23,
   "gana_count": null,
   "line_count": 4,
   "poet_id": 23,
   "poet_name": "త్రిపురనేని రామస్వామి",
   "meter_id": 8,
   "meter_name": "ఉత్పలమాల"
  },
  {
   "id": 2529,
   "title": "ధూర్తమానవా శతకము - 9",
   "text": "బలి యేపాపముఁ జేసినాఁ డతనిపై-వైరంబు నాకేల? త\nద్బలి రాజ్యంబు హరింప వంచకుండనై-ధర్మంబుఁ బోద్రోసి దో\nర్బలహీనుండగు నింద్రుఁ బ్రోవ నవతా-రం బెత్తినా నంచు లో\nకులు నమ్మన్‌ వచియింతు వింకయిన బొం-కుల్‌ మానవా? మానవా!",
   "literary_form": "శతకం",
   "source": "ధూర్తమానవా శతకము",
   "kanda": null,
   "flags": null,
   "rating": null,
   "prathipadartham": [
    {
     "word": "బలి",
     "meaning": "మహాబలి చక్రవర్తి"
    },
    {
     "word": "ఏ",
     "meaning": "ఏ విధమైన"
    },
    {
     "word": "పాపమున్",
     "meaning": "పాపమును"
    },
    {
     "word": "చేసినాడు",
     "meaning": "చేసాడు"
    },
    {
     "word": "అతనిపై",
     "meaning": "అతని మీద"
    },
    {
     "word": "వైరంబు",
     "meaning": "పగ"
    },
    {
     "word": "నాకేల",
     "meaning": "నాకెందుకు"
    },
    {
     "word": "తద్బలి",
     "meaning": "ఆ బలి చక్రవర్తి యొక్క"
    },
    {
     "word": "రాజ్యంబు",
     "meaning": "రాజ్యాన్ని"
    },
    {
     "word": "హరింప",
     "meaning": "అపహరించడానికి"
    },
    {
     "word": "వంచకుండనై",
     "meaning": "మోసగాడినై"
    },
    {
     "word": "ధర్మంబున్",
     "meaning": "ధర్మాన్ని"
    },
    {
     "word": "పోద్రోసి",
     "meaning": "తొలగించి"
    },
    {
     "word": "దోర్బలహీనుండగు",
     "meaning": "భుజబలం లేని బలహీనుడైన"
    },
    {
     "word": "ఇంద్రున్",
     "meaning": "ఇంద్రుడిని"
    },
    {
     "word": "బ్రోవ",
     "meaning": "రక్షించడానికి"
    },
    {
     "word": "అవతారంబు",
     "meaning": "అవతారాన్ని"
    },
    {
     "word": "ఎత్తినాను",
     "meaning": "ధరించాను"
    },
    {
     "word": "అంచు",
     "meaning": "అని"
    },
    {
     "word": "లోకులు",
     "meaning": "ప్రజలు"
    },
    {
     "word": "నమ్మన్",
     "meaning": "నమ్మేటట్లుగా"
    },
    {
     "word": "వచియింతువు",
     "meaning": "చెబుతున్నావు"
    },
    {
     "word": "ఇంకనైన",
     "meaning": "ఇప్పటికైనా"
    },
    {
     "word": "బొంకులు",
     "meaning": "అబద్ధపు మాటలు"
    },
    {
     "word": "మానవా",
     "meaning": "ఓ మనిషి"
    }
   ],
   "bhavam": "ఓ మనిషి! మహాబలి చక్రవర్తి ఏ పాపం చేశాడని నీవు అతనిని ద్వేషించావు? నీవు వంచకుడవై ధర్మాన్ని పక్కనపెట్టి, కేవలం బలహీనుడైన ఇంద్రుడిని కాపాడటానికి అవతారమెత్తానని చెప్పడం ఎంతవరకు సమంజసం? ఇప్పటికైనా ఇలాంటి అబద్ధపు మాటలను మానుకో.",
   "word_count": 26,
   "gana_count": null,
   "line_count": 4,
   "poet_id": 23,
   "poet_name": "త్రిపురనేని రామస్వామి",
   "meter_id": 3,
   "meter_name": "Unknown"
  },
  {
   "id": 2530,
   "title": "ధూర్తమానవా శతకము - 10",
   "text": "పరులను, ధర్మదూరులను,-బంధురపాపనిమగ్నచిత్తులన్‌\nగరుణను గాచి ప్రోచుటకు-గా మఱితో బలిచక్రవర్తినిన్‌\nదిరిపెము నెత్తినాఁడ నని-దేబిరిగొట్టుమొగంబ, యెల్లెడన్‌\nనిరతము చాటుచుండెదవె!-నీపనిఁ బట్టెద ధూర్తమానవా!",
   "literary_form": "శతకం",
   "source": "ధూర్తమానవా శతకము",
   "kanda": null,
   "flags": null,
   "rating": "gold",
   "prathipadartham": [
    {
     "word": "పరులను",
     "meaning": "అన్యులను (ఇతరులను)"
    },
    {
     "word": "ధర్మదూరులను",
     "meaning": "ధర్మానికి దూరంగా ఉన్నవారిని"
    },
    {
     "word": "బంధురపాపనిమగ్నచిత్తులన్‌",
     "meaning": "అధికమైన పాపకార్యాలలో మునిగిపోయిన మనస్సు కలవారిని"
    },
    {
     "word": "కరుణను",
     "meaning": "దయతో"
    },
    {
     "word": "గాచి",
     "meaning": "రక్షించి"
    },
    {
     "word": "ప్రోచుటకు",
     "meaning": "కాపాడటానికి"
    },
    {
     "word": "గా",
     "meaning": "కోసం"
    },
    {
     "word": "మఱితో",
     "meaning": "మరియొకరితో"
    },
    {
     "word": "బలిచక్రవర్తినిన్‌",
     "meaning": "బలి చక్రవర్తిని"
    },
    {
     "word": "దిరిపెము",
     "meaning": "భిక్ష (అడుక్కోవడం)"
    },
    {
     "word": "ఎత్తినాఁడను",
     "meaning": "అడిగాను అని"
    },
    {
     "word": "అని",
     "meaning": "అని"
    },
    {
     "word": "దేబిరిగొట్టుమొగంబ",
     "meaning": "దౌర్భాగ్యపు మొహం వేసుకుని"
    },
    {
     "word": "ఎల్లెడన్‌",
     "meaning": "అన్ని చోట్లా"
    },
    {
     "word": "నిరతము",
     "meaning": "ఎల్లప్పుడూ"
    },
    {
     "word": "చాటుచుండెదవె",
     "meaning": "ప్రకటిస్తూ ఉంటావా?"
    },
    {
     "word": "నీపనిఁ",
     "meaning": "నీ పనిని"
    },
    {
     "word": "బట్టెద",
     "meaning": "పట్టుకుంటాను (ఎండగడతాను)"
    },
    {
     "word": "ధూర్తమానవా",
     "meaning": "దుర్మార్గుడవైన మనిషి"
    }
   ],
   "bhavam": "ఓ దుర్మార్గుడా! ఇతరులను, ధర్మానికి దూరమైన వారిని, ఘోరపాపాలలో మునిగిపోయిన వారిని రక్షించడం కోసం విష్ణువు బలి చక్రవర్తిని భిక్ష అడిగాడని, నువ్వు దౌర్భాగ్యపు మొహం వేసుకుని ప్రతిచోటా ఎందుకు చాటి చెబుతున్నావు? నీ ఈ మోసపు పనులని నేను పట్టుకుంటాను (ఎండగడతాను).",
   "word_count": 15,
   "gana_count": null,
   "line_count": 4,
   "poet_id": 23,
   "poet_name": "త్రిపురనేని రామస్వామి",
   "meter_id": 9,
   "meter_name": "చంపకమాల"
  },
  {
   "id": 2531,
   "title": "ధూర్తమానవా శతకము - 11",
   "text": "తనువెల్లన్‌ గులపెట్టి జీర్ణసుఖ రు-గ్దద్రువ్యధాపీడచే\nత నహోరాత్రులు కామతృప్తి కొరకై-దారాడు స్వర్లోక నా\nథుని పక్షంబయి దానశీలుని మహ-త్పూజ్యున్‌ బలిన్‌ సత్యవా\nక్యనిరూఢున్‌ బొరియించినా ననుచుఁ బ-ల్కన్‌ జూతువే మానవా!",
   "literary_form": "శతకం",
   "source": "ధూర్తమానవా శతకము",
   "kanda": null,
   "flags": null,
   "rating": "gold",
   "prathipadartham": [
    {
     "word": "తనువు",
     "meaning": "శరీరం"
    },
    {
     "word": "ఎల్లన్",
     "meaning": "అంతటా"
    },
    {
     "word": "గులపెట్టి",
     "meaning": "రోగంతో బాధపడుతూ"
    },
    {
     "word": "జీర్ణసుఖ",
     "meaning": "జీర్ణక్రియకు సంబంధించిన సుఖం"
    },
    {
     "word": "రుగ్దద్రువ్యధాపీడచే",
     "meaning": "రోగం మరియు బాధల పీడతో"
    },
    {
     "word": "అహోరాత్రులు",
     "meaning": "పగలు రాత్రి"
    },
    {
     "word": "కామతృప్తి",
     "meaning": "భోగ వాంఛల తీర్చుకోవడం"
    },
    {
     "word": "కొరకై",
     "meaning": "కోసం"
    },
    {
     "word": "తారాడు",
     "meaning": "తిరిగే"
    },
    {
     "word": "స్వర్లోకనాథుని",
     "meaning": "ఇంద్రుని"
    },
    {
     "word": "పక్షంబయి",
     "meaning": "పక్షాన ఉండి"
    },
    {
     "word": "దానశీలుని",
     "meaning": "దాన గుణం కలిగిన వానిని"
    },
    {
     "word": "మహత్పూజ్యున్",
     "meaning": "గొప్పగా పూజించదగిన వానిని"
    },
    {
     "word": "బలిన్",
     "meaning": "బలి చక్రవర్తిని"
    },
    {
     "word": "సత్యవాక్యనిరూఢున్",
     "meaning": "సత్యవ్రతుడైన వానిని"
    },
    {
     "word": "బొరియించినాను",
     "meaning": "మోసగించాను"
    },
    {
     "word": "అనుచున్",
     "meaning": "అని"
    },
    {
     "word": "పల్కన్",
     "meaning": "చెప్పడానికి"
    },
    {
     "word": "జూతువే",
     "meaning": "ప్రయత్నిస్తావా?"
    },
    {
     "word": "మానవా",
     "meaning": "ఓ మనిషి"
    }
   ],
   "bhavam": "ఓ మనిషీ! రోగాలతో, శారీరక బాధలతో నిరంతరం భోగవాంఛల కోసం తపించే ఇంద్రుని పక్షాన నిలబడి, దానశీలుడు, పూజ్యుడు, సత్యవంతుడైన బలి చక్రవర్తిని మోసగించాను అని చెప్పుకోవడానికి నువ్వు సిగ్గుపడవా? ఇంద్రుని నీచమైన చేష్టలను సమర్థించుకోవడం తప్పు.",
   "word_count": 22,
   "gana_count": null,
   "line_count": 4,
   "poet_id": 23,
   "poet_name": "త్రిపురనేని రామస్వామి",
   "meter_id": 7,
   "meter_name": "మత్తేభవిక్రీడితము"
  },
  {
   "id": 2532,
   "title": "ధూర్తమానవా శతకము - 12",
   "text": "ఒక్కఁడు తండ్రిఁ జంపెనని-యోరిమిలేకయె గండ్రగొడ్డటన్‌\nజక్కడగింప ధర్మువగు-నా కులమంతయు? దీనిజేయ నే\nనొక్కఁడనే కనంబడితి-నో! యిటువంటివి పూర్వమందు నే\nదిక్కులనేని విన్పడెనె?-తిక్కవదల్చెద ధూర్తమానవా!",
   "literary_form": "శతకం",
   "source": "ధూర్తమానవా శతకము",
   "kanda": null,
   "flags": null,
   "rating": "gold",
   "prathipadartham": [
    {
     "word": "ఒక్కఁడు",
     "meaning": "ఒక వ్యక్తి"
    },
    {
     "word": "తండ్రిఁ",
     "meaning": "తండ్రిని"
    },
    {
     "word": "జంపెనని",
     "meaning": "చంపాడని"
    },
    {
     "word": "యోరిమిలేకయె",
     "meaning": "ఓర్పు లేకపోవడముచేతనే"
    },
    {
     "word": "గండ్రగొడ్డటన్‌",
     "meaning": "గండ్రగొడ్డలితో"
    },
    {
     "word": "జక్కడగింప",
     "meaning": "అణచివేయడం లేదా చంపడం"
    },
    {
     "word": "ధర్మువగునా",
     "meaning": "ధర్మం అవుతుందా?"
    },
    {
     "word": "కులమంతయు?",
     "meaning": "ఆ వంశంలోని వారందరినీ?"
    },
    {
     "word": "దీనిజేయ",
     "meaning": "ఈ పని చేయడానికి"
    },
    {
     "word": "నేనొక్కఁడనే",
     "meaning": "నేను ఒక్కడినే"
    },
    {
     "word": "కనంబడితి",
     "meaning": "కనిపించానా?"
    },
    {
     "word": "ఓ!",
     "meaning": "అయ్యో!"
    },
    {
     "word": "యిటువంటివి",
     "meaning": "ఇలాంటి అన్యాయపు పనులు"
    },
    {
     "word": "పూర్వమందు",
     "meaning": "పాతకాలంలో"
    },
    {
     "word": "నేదిక్కులనేని",
     "meaning": "ఏ దిక్కులలోనైనా"
    },
    {
     "word": "విన్పడెనె?",
     "meaning": "వినిపించాయా?"
    },
    {
     "word": "తిక్కవదల్చెద",
     "meaning": "నీ పిచ్చితనాన్ని వదిలిస్తాను"
    },
    {
     "word": "ధూర్తమానవా!",
     "meaning": "దుర్మార్గుడవైన మనిషీ!"
    }
   ],
   "bhavam": "ఒక వ్యక్తి తండ్రిని చంపాడన్న నెపంతో, ఓర్పు లేకుండా ఆ వంశంలోని వారందరినీ గండ్రగొడ్డలితో నరికి చంపడం ధర్మం అనిపించుకుంటుందా? ఇలాంటి అన్యాయమైన పనిని చేయడానికి నేనే దొరికానా? అసలు పూర్వకాలంలో ఎక్కడైనా ఇలాంటి దారుణాలు జరగడం విన్నామా? ఓ దుర్మార్గుడా! నీ బుర్రలో ఉన్న ఈ పిచ్చి ఆలోచనలను వదిలించుకో.",
   "word_count": 17,
   "gana_count": null,
   "line_count": 4,
   "poet_id": 23,
   "poet_name": "త్రిపురనేని రామస్వామి",
   "meter_id": 8,
   "meter_name": "ఉత్పలమాల"
  },
  {
   "id": 2533,
   "title": "ధూర్తమానవా శతకము - 13",
   "text": "ఉడుగక తొల్లి పెండ్లమును-నొక్కతె నామెడ కంటఁగట్టి యా\nబిడ నెవఁడో హరించె నని-వెంగలిమాటలు చెప్పి యామెకై\nయెడతెగకుండ బావురని-యేడ్చితినంచును నెన్నిరోజులో\nబడబడ పెద్దగ్రంథములు-వ్రాసితివేమిర? ధూర్తమానవా!",
   "literary_form": "శతకం",
   "source": "ధూర్తమానవా శతకము",
   "kanda": null,
   "flags": null,
   "rating": null,
   "prathipadartham": [
    {
     "word": "ఉడుగక",
     "meaning": "మానకుండా"
    },
    {
     "word": "తొల్లి",
     "meaning": "పూర్వం"
    },
    {
     "word": "పెండ్లమును-నొక్కతెన్",
     "meaning": "ఒక భార్యను"
    },
    {
     "word": "నామెడ",
     "meaning": "నా మెడకు"
    },
    {
     "word": "కంటఁగట్టి",
     "meaning": "కట్టేసి"
    },
    {
     "word": "యాబిడ",
     "meaning": "ఆ స్త్రీని"
    },
    {
     "word": "నెవఁడో",
     "meaning": "ఎవడో ఒకడు"
    },
    {
     "word": "హరించెనని",
     "meaning": "ఎత్తుకుపోయాడు అని"
    },
    {
     "word": "వెంగలిమాటలు",
     "meaning": "పిచ్చి మాటలు"
    },
    {
     "word": "చెప్పి",
     "meaning": "చెప్పుకుంటూ"
    },
    {
     "word": "యామెకై",
     "meaning": "ఆమె కోసం"
    },
    {
     "word": "యెడతెగకుండ",
     "meaning": "ఎడతెరిపి లేకుండా"
    },
    {
     "word": "బావురని-యేడ్చితినంచును",
     "meaning": "బావురుమని ఏడ్చాను అని"
    },
    {
     "word": "నెన్నిరోజులో",
     "meaning": "ఎన్ని రోజులు"
    },
    {
     "word": "బడబడ",
     "meaning": "వేగంగా/గొడవగా"
    },
    {
     "word": "పెద్దగ్రంథములు",
     "meaning": "పెద్ద పెద్ద పుస్తకాలు"
    },
    {
     "word": "వ్రాసితివేమిర",
     "meaning": "ఎందుకు వ్రాశావురా"
    },
    {
     "word": "ధూర్తమానవా",
     "meaning": "దుర్మార్గుడవైన ఓ మానవుడా"
    }
   ],
   "bhavam": "ఓ దుర్మార్గుడా! పూర్వం నీకు ఎవరైనా ఒక భార్యను కట్టబెడితే, ఆమెను ఎవడో ఎత్తుకుపోయాడని పిచ్చి పిచ్చి మాటలు చెప్పుకుంటూ, ఆమె కోసం ఎడతెరిపి లేకుండా ఏడ్చినట్లుగా ఎన్ని రోజులు గడిపి, ఆ విషయమై పెద్ద పెద్ద పుస్తకాలు ఎందుకు వ్రాశావు? నీ ఈ చేష్టలు ఎంత అర్థరహితం!",
   "word_count": 18,
   "gana_count": null,
   "line_count": 4,
   "poet_id": 23,
   "poet_name": "త్రిపురనేని రామస్వామి",
   "meter_id": 3,
   "meter_name": "Unknown"
  },
  {
   "id": 2534,
   "title": "ధూర్తమానవా శతకము - 14",
   "text": "మిడిమేలంబుగఁ దెచ్చిపెట్టితివిగా-మేనత్తతోఁ గూటమిన్‌\nబడి మువ్వంకల ముండతోడ మధురా-పట్నంబులోఁ గూటమిన్‌\nమెడకుంగట్టితి వెంతవాఁడవుర! నీ-మిట్టాటలన్‌ మానవా!\nకడికండల్‌ తెగఁగోసివైచెదను గా-కశ్రేణికిన్‌ మానవా!",
   "literary_form": "శతకం",
   "source": "ధూర్తమానవా శతకము",
   "kanda": null,
   "flags": null,
   "rating": "gold",
   "prathipadartham": [
    {
     "word": "మిడిమేలంబుగ",
     "meaning": "అహంకారంతో (గర్వంతో)"
    },
    {
     "word": "తెచ్చిపెట్టితివి",
     "meaning": "తెచ్చిపెట్టుకున్నావు (కొనితెచ్చుకున్నావు)"
    },
    {
     "word": "మేనత్తతోఁ గూటమిన్‌",
     "meaning": "మేనత్తతో అక్రమ సంబంధం పెట్టుకుని"
    },
    {
     "word": "బడి",
     "meaning": "పడి (లోబడి)"
    },
    {
     "word": "మువ్వంకల ముండతోడ",
     "meaning": "దుర్మార్గురాలైన స్త్రీతో"
    },
    {
     "word": "మధురాపట్నంబులో",
     "meaning": "మధుర నగరంలో"
    },
    {
     "word": "గూటమిన్‌",
     "meaning": "సహవాసంతో"
    },
    {
     "word": "మెడకుంగట్టితివి",
     "meaning": "మెడకు కట్టుకున్నావు (నిందలు తెచ్చుకున్నావు)"
    },
    {
     "word": "ఎంతవాఁడవురా!",
     "meaning": "ఎంతటి నీచుడివిరా!"
    },
    {
     "word": "నీ మిట్టాటలన్‌",
     "meaning": "నీ గర్వపు పనులతో"
    },
    {
     "word": "మానవా!",
     "meaning": "ఓ మనిషి (నిర్లక్ష్యంగా సంబోధన)"
    },
    {
     "word": "కడికండల్‌",
     "meaning": "ముక్కలు ముక్కలుగా"
    },
    {
     "word": "తెగఁగోసివైచెదను",
     "meaning": "నరికివేస్తాను"
    },
    {
     "word": "గాకశ్రేణికిన్‌",
     "meaning": "కాకుల సమూహానికి (ఆహారంగా)"
    }
   ],
   "bhavam": "ఓ మనిషీ! అహంకారంతో మేనత్తతో అక్రమ సంబంధం పెట్టుకుని, మధుర నగరంలో ఒక దుర్మార్గురాలైన స్త్రీతో కూడి నీవు తెచ్చుకున్న ఈ చెడు పేరును చూస్తుంటే నీవు ఎంతటి నీచుడవనిపిస్తోంది. నీ గర్వపు పనుల వల్ల నీ మెడకు పెద్ద నిందనే కట్టుకున్నావు. జాగ్రత్త! నీవు ఇలాగే ప్రవర్తిస్తే, నీ శరీరాన్ని ముక్కలు ముక్కలుగా నరికి కాకులకు ఆహారంగా వేస్తాను.",
   "word_count": 16,
   "gana_count": null,
   "line_count": 4,
   "poet_id": 23,
   "poet_name": "త్రిపురనేని రామస్వామి",
   "meter_id": 7,
   "meter_name": "మత్తేభవిక్రీడితము"
  },
  {
   "id": 2535,
   "title": "ధూర్తమానవా శతకము - 15",
   "text": "అవతారంబులనెత్తి చేయగల న-న్యాయంబు లన్నింటి నే\nనవతారంబుల నెత్తకుండ మఱి చే-యన్‌ శక్తిలే దంచు న\nన్నవమానించితి వింతకాల మిటు? ని-న్నాపాదమస్తంబుగా\nనివురుంజేసెద నెవ్వరడ్డపడగా-నీ కుండిరో మానవా!",
   "literary_form": "శతకం",
   "source": "ధూర్తమానవా శతకము",
   "kanda": null,
   "flags": null,
   "rating": "gold",
   "prathipadartham": [
    {
     "word": "మానవా",
     "meaning": "ఓ మానవుడా"
    },
    {
     "word": "అవతారంబులనెత్తి",
     "meaning": "అవతారాలు ధరించి"
    },
    {
     "word": "చేయగల",
     "meaning": "చేయగలిగిన"
    },
    {
     "word": "అన్యాయంబులన్నింటి",
     "meaning": "అన్యాయాలన్నింటిని"
    },
    {
     "word": "నేను",
     "meaning": "నేను"
    },
    {
     "word": "అవతారంబులనెత్తకుండ",
     "meaning": "అవతారాలు ఎత్తకుండా"
    },
    {
     "word": "మఱి",
     "meaning": "ఇకపై"
    },
    {
     "word": "చేయన్‌",
     "meaning": "చేయడానికి"
    },
    {
     "word": "శక్తిలేదంచు",
     "meaning": "శక్తి లేదని"
    },
    {
     "word": "నన్ను",
     "meaning": "నన్ను"
    },
    {
     "word": "అవమానించితి",
     "meaning": "అవమానించావు"
    },
    {
     "word": "ఇంతకాలం",
     "meaning": "ఇంతకాలంగా"
    },
    {
     "word": "ఇటు",
     "meaning": "ఈ విధంగా"
    },
    {
     "word": "నిన్ను",
     "meaning": "నిన్ను"
    },
    {
     "word": "ఆపాదమస్తంబుగా",
     "meaning": "పాదాల నుండి తల వరకు (పూర్తిగా)"
    },
    {
     "word": "ఇవురుంజేసెద",
     "meaning": "భస్మం చేస్తాను"
    },
    {
     "word": "ఎవ్వరు",
     "meaning": "ఎవరు"
    },
    {
     "word": "అడ్డపడగా",
     "meaning": "అడ్డుపడతారు"
    },
    {
     "word": "నీకుండిరో",
     "meaning": "నీకు"
    }
   ],
   "bhavam": "ఓ మానవుడా! నేను అవతారాలు ఎత్తి చేసే అన్యాయాలను, ఇకపై నేను అవతారాలు ఎత్తకపోతే చేయలేనని భావించి, ఇంతకాలం నన్ను అవమానించావు. నిన్ను తల నుండి పాదాల వరకు భస్మం చేస్తాను, అడ్డుపడటానికి నీకెవరున్నారు?",
   "word_count": 20,
   "gana_count": null,
   "line_count": 4,
   "poet_id": 23,
   "poet_name": "త్రిపురనేని రామస్వామి",
   "meter_id": 7,
   "meter_name": "మత్తేభవిక్రీడితము"
  },
  {
   "id": 2536,
   "title": "ధూర్తమానవా శతకము - 16",
   "text": "స్మృతులన్‌ వ్రాసితి నందు; వాస్మృతులలోఁ-జిత్రించి శ్రుత్యర్థముల్‌\nప్రతిపాదించితినందు; వయ్యది నిజం-బా? యెంతకాలంబు దు\nష్కృతి సాగింతువు, లోకవంచనములన్‌-జేయింతువో, చేతువో\nపతితాత్మా, యిఁకనైన యీ వెడఁగు త్రో-వల్‌ మానవా? మానవా!",
   "literary_form": "శతకం",
   "source": "ధూర్తమానవా శతకము",
   "kanda": null,
   "flags": null,
   "rating": "gold",
   "prathipadartham": [
    {
     "word": "స్మృతులన్‌",
     "meaning": "స్మృతులలో"
    },
    {
     "word": "వ్రాసితి",
     "meaning": "రాశాను"
    },
    {
     "word": "అందు",
     "meaning": "అందులో"
    },
    {
     "word": "ఆ స్మృతులలో",
     "meaning": "ఆ స్మృతుల ద్వారా"
    },
    {
     "word": "చిత్రించి",
     "meaning": "చిత్రముగా (అందంగా/అద్భుతంగా) వర్ణించి"
    },
    {
     "word": "శ్రుత్యర్థముల్‌",
     "meaning": "వేదాల యొక్క అర్థాలను"
    },
    {
     "word": "ప్రతిపాదించితినందు",
     "meaning": "ప్రతిపాదించానని అంటున్నావా"
    },
    {
     "word": "అయ్యది",
     "meaning": "అది"
    },
    {
     "word": "నిజంబా",
     "meaning": "నిజమా"
    },
    {
     "word": "ఎంతకాలంబు",
     "meaning": "ఎన్నాళ్లు"
    },
    {
     "word": "దుష్కృతి",
     "meaning": "పాపపు పనులు"
    },
    {
     "word": "సాగింతువు",
     "meaning": "చేస్తూ ఉంటావు"
    },
    {
     "word": "లోకవంచనములన్‌",
     "meaning": "ప్రపంచాన్ని మోసం చేసే పనులను"
    },
    {
     "word": "జేయింతువో",
     "meaning": "ఇతరులతో చేయిస్తావో"
    },
    {
     "word": "చేతువో",
     "meaning": "నీవు చేస్తావో"
    },
    {
     "word": "పతితాత్మా",
     "meaning": "పతనమైన ఆత్మ కలవాడా"
    },
    {
     "word": "ఇఁకనైన",
     "meaning": "ఇప్పటికైనా"
    },
    {
     "word": "ఈ",
     "meaning": "ఈ"
    },
    {
     "word": "వెడఁగు త్రోవల్‌",
     "meaning": "చెడ్డ మార్గాలను (మూర్ఖపు పద్ధతులను)"
    },
    {
     "word": "మానవా",
     "meaning": "మానుకోవా (వదిలేయవా)"
    },
    {
     "word": "మానవా",
     "meaning": "ఓ మనిషీ"
    }
   ],
   "bhavam": "ఓ మనిషీ! స్మృతులను వ్రాశానని, వాటి ద్వారా వేదార్థాలను అద్భుతంగా వివరించానని నీవు చెప్పుకుంటున్నావు. ఇది నిజమేనా? ఇలాంటి పాపపు పనులు, లోకవంచనలు ఇంకెన్నాళ్లు చేస్తావు? ఇతరులతో చేయిస్తావు? పతనమైన ఆత్మ కలవాడా, ఇప్పటికైనా ఇటువంటి మూర్ఖపు పద్ధతులను వదిలిపెట్టవా?",
   "word_count": 21,
   "gana_count": null,
   "line_count": 4,
   "poet_id": 23,
   "poet_name": "త్రిపురనేని రామస్వామి",
   "meter_id": 7,
   "meter_name": "మత్తేభవిక్రీడితము"
  },
  {
   "id": 2537,
   "title": "ధూర్తమానవా శతకము - 17",
   "text": "కలలోఁ గన్పడుచుండు బట్టబయలన్‌-గన్పట్ట రాకుండు గ\nఱ్దలు గ్రంథంబులు జెప్పుఁ గట్టెదుటఁ బ్ర-త్యక్షంబుఁ జెప్పండు లో\nకులు కల్లోలపడంగ నీగతిని ట-క్కుల్‌ చెప్పు మాయావికిన్‌\nతలతిక్కన్‌ వదలింతు నీపయిని చి-త్తభ్రాంతిపో మానవా!",
   "literary_form": "శతకం",
   "source": "ధూర్తమానవా శతకము",
   "kanda": null,
   "flags": null,
   "rating": "gold",
   "prathipadartham": [
    {
     "word": "కలలోన్",
     "meaning": "కలలో"
    },
    {
     "word": "కన్పడుచుండు",
     "meaning": "కనిపిస్తూ ఉంటాడు"
    },
    {
     "word": "బట్టబయలన్",
     "meaning": "స్పష్టంగా కనిపించే చోట"
    },
    {
     "word": "కన్పట్ట రాకుండు",
     "meaning": "కనిపించడు"
    },
    {
     "word": "గఱ్దలు",
     "meaning": "గొప్పలు"
    },
    {
     "word": "గ్రంథంబులు",
     "meaning": "శాస్త్రాలను"
    },
    {
     "word": "జెప్పు",
     "meaning": "చెబుతాడు"
    },
    {
     "word": "కట్టెదుట",
     "meaning": "ఎదురుగా"
    },
    {
     "word": "ప్రత్యక్షంబు",
     "meaning": "నిజమైన సాక్షాత్కారాన్ని"
    },
    {
     "word": "జెప్పండు",
     "meaning": "చెప్పలేడు"
    },
    {
     "word": "లోకులు",
     "meaning": "జనులు"
    },
    {
     "word": "కల్లోలపడంగ",
     "meaning": "అల్లకల్లోలమయ్యేలా"
    },
    {
     "word": "ఈగతిని",
     "meaning": "ఈ విధంగా"
    },
    {
     "word": "టక్కులు",
     "meaning": "మోసపు మాటలు"
    },
    {
     "word": "జెప్పు",
     "meaning": "చెప్పే"
    },
    {
     "word": "మాయావికిన్",
     "meaning": "మోసగాడికి"
    },
    {
     "word": "తలతిక్కన్",
     "meaning": "పిచ్చి ఆలోచనలను"
    },
    {
     "word": "వదలింతు",
     "meaning": "వదిలిస్తాను"
    },
    {
     "word": "నీపయిని",
     "meaning": "నీ మీద"
    },
    {
     "word": "చిత్తభ్రాంతిపో",
     "meaning": "మనసులో ఉన్న భ్రమ తొలగిపోతుంది"
    },
    {
     "word": "మానవా",
     "meaning": "ఓ మనిషీ"
    }
   ],
   "bhavam": "ఓ మనిషీ! కలలో మాత్రం కనిపిస్తూ, నిత్య జీవితంలో ఎదురుగా ఉంటే కనిపించని దేవుళ్లని, మాయాజాలపు శాస్త్రాలని చెబుతూ ప్రజలను గందరగోళానికి గురిచేసే ఈ మోసగాళ్ల పిచ్చిని వదిలించుకో. నీ మనసులో ఉన్న భ్రమలను తొలగించుకొని విచక్షణతో ఆలోచించు.",
   "word_count": 23,
   "gana_count": null,
   "line_count": 4,
   "poet_id": 23,
   "poet_name": "త్రిపురనేని రామస్వామి",
   "meter_id": 7,
   "meter_name": "మత్తేభవిక్రీడితము"
  },
  {
   "id": 2538,
   "title": "ధూర్తమానవా శతకము - 18",
   "text": "ఈ టకటొంకు లేమిటికి?-నిల్లును వాకిలిఁ గట్టిపెట్టి యే\nటేటను బెండ్లి సేయుమని-యే నెపుడైనను గోరియుంటినే!\nచీటికి మాటికిన్‌ బరుల-జేబులు గొట్టుట ధర్మమార్గమే?\nఏటికి నీయబద్ధ మర-రే! యిఁక సాగునె? ధూర్తమానవా!",
   "literary_form": "శతకం",
   "source": "ధూర్తమానవా శతకము",
   "kanda": null,
   "flags": null,
   "rating": "gold",
   "prathipadartham": [
    {
     "word": "ఈ",
     "meaning": "ఈ"
    },
    {
     "word": "టకటొంకు",
     "meaning": "డంబాలు, వ్యర్థమైన ఆర్భాటాలు"
    },
    {
     "word": "లేమిటికి",
     "meaning": "ఎందుకు"
    },
    {
     "word": "నిల్లును",
     "meaning": "ఇంటిని"
    },
    {
     "word": "వాకిలిన్",
     "meaning": "వాకిలిని"
    },
    {
     "word": "గట్టిపెట్టి",
     "meaning": "బంధించి"
    },
    {
     "word": "ఏటేటను",
     "meaning": "ఏడాది ఏడాదికి"
    },
    {
     "word": "పెండ్లి",
     "meaning": "వివాహం"
    },
    {
     "word": "సేయుమని",
     "meaning": "చేయమని"
    },
    {
     "word": "ఏను",
     "meaning": "నేను"
    },
    {
     "word": "ఎపుడైనను",
     "meaning": "ఎప్పుడైనా"
    },
    {
     "word": "గోరియుంటినే",
     "meaning": "కోరుకున్నానా"
    },
    {
     "word": "చీటికి",
     "meaning": "ప్రతి విషయానికి"
    },
    {
     "word": "మాటికిన్",
     "meaning": "మళ్ళీ మళ్ళీ"
    },
    {
     "word": "పరుల",
     "meaning": "ఇతరుల"
    },
    {
     "word": "జేబులు",
     "meaning": "జేబులను"
    },
    {
     "word": "గొట్టుట",
     "meaning": "కొల్లగొట్టడం, దొంగిలించడం"
    },
    {
     "word": "ధర్మమార్గమే",
     "meaning": "నీతిమార్గమా"
    },
    {
     "word": "ఏటికి",
     "meaning": "ఎందుకు"
    },
    {
     "word": "నీ",
     "meaning": "నీ యొక్క"
    },
    {
     "word": "అబద్ధపు",
     "meaning": "అసత్యపు"
    },
    {
     "word": "అర",
     "meaning": "మాటలు"
    },
    {
     "word": "రే",
     "meaning": "ఓయీ"
    },
    {
     "word": "ఇక",
     "meaning": "ఇకమీదట"
    },
    {
     "word": "సాగునె",
     "meaning": "చెల్లుతుందా"
    },
    {
     "word": "ధూర్తమానవా",
     "meaning": "దుర్మార్గుడా"
    }
   ],
   "bhavam": "ఓ దుర్మార్గుడా! ఈ వ్యర్థమైన ఆర్భాటాలు ఎందుకు? ఇల్లు వాకిలి మూసిపెట్టి ఏటా పెళ్లి చేసుకోమని నేను ఎప్పుడైనా నిన్ను కోరానా? ప్రతి విషయానికి ఇతరుల జేబులు కొట్టడం ధర్మమార్గం అవుతుందా? ఓయీ! ఇకనైనా నీ అబద్ధపు మాటలు చాలించు, ఇక నీ మాయలు సాగవు.",
   "word_count": 22,
   "gana_count": null,
   "line_count": 4,
   "poet_id": 23,
   "poet_name": "త్రిపురనేని రామస్వామి",
   "meter_id": 8,
   "meter_name": "ఉత్పలమాల"
  },
  {
   "id": 2539,
   "title": "ధూర్తమానవా శతకము - 19",
   "text": "బొక్కెడుకూడు పట్టుమని-పొట్టకు తింటినె యొక్కపూటయేన్‌?\nజక్కగ నొంటినిండ నొక-జానెడు గుడ్డను గప్పుకొంటినే!\nఒక్కటియేని మ్రుచ్చిలిక-యుంచితివే? యిఁక నీదుపాటు లే\nనక్కయుఁ గుక్కయున్‌ బడదు;-నా పలుకుల్‌ విను ధూర్తమానవా!",
   "literary_form": "శతకం",
   "source": "ధూర్తమానవా శతకము",
   "kanda": null,
   "flags": null,
   "rating": "gold",
   "prathipadartham": [
    {
     "word": "ధూర్తమానవా",
     "meaning": "దుర్మార్గుడవైన ఓ మానవుడా"
    },
    {
     "word": "బొక్కెడుకూడు",
     "meaning": "ఒక గుప్పెడు అన్నం"
    },
    {
     "word": "పట్టుమని",
     "meaning": "గట్టిగా లెక్కవేస్తే"
    },
    {
     "word": "పొట్టకు",
     "meaning": "కడుపు నింపుకోవడానికి"
    },
    {
     "word": "తింటినె",
     "meaning": "తినగలిగావా?"
    },
    {
     "word": "యొక్కపూటయేన్‌",
     "meaning": "కనీసం ఒక్క పూటయినా?"
    },
    {
     "word": "జక్కగ",
     "meaning": "సరిగ్గా"
    },
    {
     "word": "నొంటినిండ",
     "meaning": "ఒంటినిండా"
    },
    {
     "word": "నొక-జానెడు గుడ్డను",
     "meaning": "ఒక జానెడు వస్త్రాన్ని"
    },
    {
     "word": "గప్పుకొంటినే",
     "meaning": "కప్పుకోగలిగావా?"
    },
    {
     "word": "ఒక్కటియేని",
     "meaning": "కనీసం ఒక్క వస్తువైనా"
    },
    {
     "word": "మ్రుచ్చిలిక",
     "meaning": "దొంగిలించి"
    },
    {
     "word": "యుంచితివే",
     "meaning": "దాచుకున్నావా?"
    },
    {
     "word": "యిఁక",
     "meaning": "ఇకమీదట"
    },
    {
     "word": "నీదుపాటులు",
     "meaning": "నీవు పడే ఈ పాట్లు (ప్రయాసలు)"
    },
    {
     "word": "నక్కయుఁ గుక్కయున్‌",
     "meaning": "నక్కకుగానీ కుక్కకుగానీ"
    },
    {
     "word": "బడదు",
     "meaning": "రాదు (అవి నీ అంతగా కష్టపడవు)"
    },
    {
     "word": "నా పలుకుల్‌",
     "meaning": "నా మాటలను"
    },
    {
     "word": "విను",
     "meaning": "ఆలకించు"
    }
   ],
   "bhavam": "ఓ దుర్మార్గుడవైన మానవుడా! నీవు కడుపు నింపుకోవడానికి కనీసం ఒక పూటైనా హాయిగా తింటున్నావా? ఒంటికి కనీసం ఒక జానెడు బట్టనైనా సరిగ్గా కప్పుకుంటున్నావా? ఏదైనా వస్తువును దొంగిలించి దాచుకుంటున్నావా? నీవు పడే ఈ వ్యర్థమైన కష్టాలు కనీసం నక్కకు లేదా కుక్కకు కూడా లేవు. కాబట్టి నా మాటలు విను.",
   "word_count": 20,
   "gana_count": null,
   "line_count": 4,
   "poet_id": 23,
   "poet_name": "త్రిపురనేని రామస్వామి",
   "meter_id": 8,
   "meter_name": "ఉత్పలమాల"
  },
  {
   "id": 2540,
   "title": "ధూర్తమానవా శతకము - 20",
   "text": "పొక్కిలిగడ్డలేక, తన-పొయ్యికిఁ గట్టెలు లేక, మంటకున్‌\nబిక్కినఁ గుండలోనికిని-బియ్యపునూకలు లేక, గంజిలో\nలెక్కకు నుప్పుగల్లయిన-లేక, కృశించెడి పేదవానికిన్‌\nఱెక్కలు డుచ్చి సిల్గుల హ-రింతువె చెప్పర, ధూర్తమానవా!",
   "literary_form": "శతకం",
   "source": "ధూర్తమానవా శతకము",
   "kanda": null,
   "flags": null,
   "rating": "gold",
   "prathipadartham": [
    {
     "word": "పొక్కిలిగడ్డలేక",
     "meaning": "కడుపులో ఆకలితో అంటుకుపోయిన పొట్ట లేక"
    },
    {
     "word": "తన-పొయ్యికిఁ",
     "meaning": "తన ఇంటి పొయ్యి మీద వంట చేయడానికి"
    },
    {
     "word": "కట్టెలు లేక",
     "meaning": "వంటచెరకు లేక"
    },
    {
     "word": "మంటకున్‌",
     "meaning": "అగ్ని వెలిగించడానికి"
    },
    {
     "word": "బిక్కినఁ",
     "meaning": "నిండిన"
    },
    {
     "word": "గుండలోనికిని-బియ్యపునూకలు లేక",
     "meaning": "కుండలో వేయడానికి కనీసం బియ్యపు నూకలు కూడా లేక"
    },
    {
     "word": "గంజిలో",
     "meaning": "తాగే గంజిలో"
    },
    {
     "word": "లెక్కకు",
     "meaning": "కనీస మాత్రంగా"
    },
    {
     "word": "నుప్పుగల్లయిన-లేక",
     "meaning": "ఉప్పు రవ్వ కూడా లేక"
    },
    {
     "word": "కృశించెడి పేదవానికిన్‌",
     "meaning": "ఆకలితో అలమటించే పేదవానికి"
    },
    {
     "word": "ఱెక్కలు డుచ్చి",
     "meaning": "రెక్కలు కట్టి (సహాయం చేసి)"
    },
    {
     "word": "సిల్గుల హ-రింతువె",
     "meaning": "వారి బాధలను పోగొడతావా"
    },
    {
     "word": "చెప్పర",
     "meaning": "చెప్పుము"
    },
    {
     "word": "ధూర్తమానవా!",
     "meaning": "ఓ నీచపు మనిషి!"
    }
   ],
   "bhavam": "ఓ నీచపు మనిషి! కనీసం కడుపు నింపుకోవడానికి బియ్యం లేక, వంట చేసుకోవడానికి కట్టెలు లేక, తాగే గంజిలో వేసుకోవడానికి ఉప్పు లేక అలమటిస్తున్న పేదవాడిని ఆదుకుంటావా? లేదా వాడి కష్టాలను కనీసం తీరుస్తావా? నిజం చెప్పు.",
   "word_count": 19,
   "gana_count": null,
   "line_count": 4,
   "poet_id": 23,
   "poet_name": "త్రిపురనేని రామస్వామి",
   "meter_id": 8,
   "meter_name": "ఉత్పలమాల"
  },
  {
   "id": 2541,
   "title": "ధూర్తమానవా శతకము - 21",
   "text": "మరణపు శయ్యమీఁద నొక-మారయినన్‌ నను దప్పకుండ సం\nస్మరణము చేసినంతటనె-స్వర్గము వచ్చునటందు, వేగతిన్‌\nబొరయును? నిట్లె నీ వెపుడు-బొంకుచునుందువు దీనికై నినున్‌\nగఱకఱ గొంతు కోసెదను-కానివి చెప్పకు ధూర్తమానవా!",
   "literary_form": "శతకం",
   "source": "ధూర్తమానవా శతకము",
   "kanda": null,
   "flags": null,
   "rating": null,
   "prathipadartham": [
    {
     "word": "మరణపు",
     "meaning": "చనిపోయే"
    },
    {
     "word": "శయ్యమీఁద",
     "meaning": "మంచం మీద"
    },
    {
     "word": "నొక-మారయినన్‌",
     "meaning": "ఒక్కసారి అయినా"
    },
    {
     "word": "నను",
     "meaning": "నన్ను"
    },
    {
     "word": "దప్పకుండ",
     "meaning": "తప్పకుండా"
    },
    {
     "word": "సంస్మరణము",
     "meaning": "జ్ఞాపకం చేసుకుంటే"
    },
    {
     "word": "చేసినంతటనె",
     "meaning": "చేయగానే"
    },
    {
     "word": "స్వర్గము",
     "meaning": "స్వర్గలోకం"
    },
    {
     "word": "వచ్చునటందు",
     "meaning": "వస్తుందని అంటున్నావు"
    },
    {
     "word": "వేగతిన్‌",
     "meaning": "ఏ విధంగా"
    },
    {
     "word": "బొరయును",
     "meaning": "లభిస్తుంది"
    },
    {
     "word": "ఇట్లె",
     "meaning": "ఇలాగే"
    },
    {
     "word": "నీవు",
     "meaning": "నువ్వు"
    },
    {
     "word": "ఎపుడు",
     "meaning": "ఎప్పుడూ"
    },
    {
     "word": "బొంకుచునుందువు",
     "meaning": "అబద్ధాలు చెబుతున్నావు"
    },
    {
     "word": "దీనికై",
     "meaning": "దీనికోసం"
    },
    {
     "word": "నినున్‌",
     "meaning": "నిన్ను"
    },
    {
     "word": "గఱకఱ",
     "meaning": "బలవంతంగా"
    },
    {
     "word": "గొంతు",
     "meaning": "కంఠం"
    },
    {
     "word": "కోసెదను",
     "meaning": "కోసేస్తాను"
    },
    {
     "word": "కానివి",
     "meaning": "అబద్ధపు విషయాలు"
    },
    {
     "word": "చెప్పకు",
     "meaning": "చెప్పవద్దు"
    },
    {
     "word": "ధూర్తమానవా",
     "meaning": "దుర్మార్గుడవైన మనిషి"
    }
   ],
   "bhavam": "చనిపోయే సమయంలో ఒక్కసారి నిన్ను తలచుకుంటే స్వర్గం వస్తుందని అబద్ధాలు చెబుతున్నావు. ఇది ఎలా సాధ్యమవుతుంది? ఇలాంటి అబద్ధాలే ఎప్పుడూ చెబుతుంటే నీ గొంతు కోసేస్తాను. ఇకనైనా పనికిరాని అబద్ధపు మాటలు కట్టిపెట్టు ఓ దుర్మార్గుడా అని కవి మందలించాడు.",
   "word_count": 21,
   "gana_count": null,
   "line_count": 4,
   "poet_id": 23,
   "poet_name": "త్రిపురనేని రామస్వామి",
   "meter_id": 3,
   "meter_name": "Unknown"
  },
  {
   "id": 2542,
   "title": "ధూర్తమానవా శతకము - 22",
   "text": "ఏ నొకజాతికూడు భుజి-యించుచు మిక్కిలి తక్కుజాతులన్‌\nహీనముగాగఁ జూతునని-యెవ్వరు సెప్పిరి నీకు వంచకా!\nమానవు లందఱున్‌ సరిస-మానులు గారొకొనాకు? మాయురే!\nమానక నీవ యిట్టి యవ-మానముఁ జేతువె ధూర్తమానవా!",
   "literary_form": "శతకం",
   "source": "ధూర్తమానవా శతకము",
   "kanda": null,
   "flags": null,
   "rating": "gold",
   "prathipadartham": [
    {
     "word": "ఏ",
     "meaning": "ఏ"
    },
    {
     "word": "నొకజాతికూడు",
     "meaning": "ఒకానొక జాతివారు వండిన ఆహారమును"
    },
    {
     "word": "భుజించుచు",
     "meaning": "తింటూ"
    },
    {
     "word": "మిక్కిలి",
     "meaning": "చాలా"
    },
    {
     "word": "తక్కుజాతులన్",
     "meaning": "తక్కువ కులాల వారిని"
    },
    {
     "word": "హీనముగాగన్",
     "meaning": "నీచంగా"
    },
    {
     "word": "జూతునని",
     "meaning": "చూస్తానని"
    },
    {
     "word": "ఎవ్వరు",
     "meaning": "ఎవరు"
    },
    {
     "word": "సెప్పిరి",
     "meaning": "చెప్పారు"
    },
    {
     "word": "నీకు",
     "meaning": "నీకు"
    },
    {
     "word": "వంచకా",
     "meaning": "మోసగాడా"
    },
    {
     "word": "మానవు లందఱున్",
     "meaning": "మనుషులందరూ"
    },
    {
     "word": "సరిసమానులు",
     "meaning": "సమానమైనవారు"
    },
    {
     "word": "గారొకొ",
     "meaning": "కారా?"
    },
    {
     "word": "నాకు",
     "meaning": "నా దృష్టిలో"
    },
    {
     "word": "మాయురే",
     "meaning": "ఆశ్చర్యము"
    },
    {
     "word": "మానక",
     "meaning": "వదలకుండా"
    },
    {
     "word": "నీవ",
     "meaning": "నువ్వే"
    },
    {
     "word": "యిట్టి",
     "meaning": "ఇటువంటి"
    },
    {
     "word": "అవమానమున్",
     "meaning": "అవమానాన్ని"
    },
    {
     "word": "జేతువె",
     "meaning": "చేస్తావా?"
    },
    {
     "word": "ధూర్తమానవా",
     "meaning": "దుర్మార్గుడా"
    }
   ],
   "bhavam": "ఓ మోసగాడా! నీకు ఎవరు చెప్పారు ఒక కులం వారు వండిన భోజనం తింటూనే, మరొక కులం వారిని తక్కువగా చూడమని? నా దృష్టిలో మనుషులందరూ సమానమే కదా! ఓ దుర్మార్గుడా! మానవత్వం లేకుండా నీవెందుకు ఇలాంటి అవమానకరమైన పనులు చేస్తున్నావు?",
   "word_count": 21,
   "gana_count": null,
   "line_count": 4,
   "poet_id": 23,
   "poet_name": "త్రిపురనేని రామస్వామి",
   "meter_id": 8,
   "meter_name": "ఉత్పలమాల"
  },
  {
   "id": 2543,
   "title": "ధూర్తమానవా శతకము - 23",
   "text": "త్వరపడకుండ సంజపడు-దాఁకను తప్పుపనుల్‌ పొనర్చి పై\nబొరుగున నున్న తోఁటలను-బూవులు మ్రుచ్చిలి కోసి తెచ్చి నా\nశిరమునఁ బోసినంతటనె-చేసిన పాపము లొక్కసారిగా\nమఱచెడునట్టి వెంగలినె-మానక యిట్టివి ధూర్తమానవా!",
   "literary_form": "శతకం",
   "source": "ధూర్తమానవా శతకము",
   "kanda": null,
   "flags": null,
   "rating": "gold",
   "prathipadartham": [
    {
     "word": "ధూర్తమానవా",
     "meaning": "దుర్మార్గుడవైన ఓ మనిషి"
    },
    {
     "word": "త్వరపడకుండ",
     "meaning": "అలక్ష్యంగా"
    },
    {
     "word": "సంజపడు-దాఁకను",
     "meaning": "సంధ్యా సమయం అయ్యే వరకు"
    },
    {
     "word": "తప్పుపనుల్",
     "meaning": "తప్పు పనులను (పాపకార్యాలను)"
    },
    {
     "word": "పొనర్చి",
     "meaning": "చేసి"
    },
    {
     "word": "పైబొరుగున నున్న",
     "meaning": "పక్కనే ఉన్న"
    },
    {
     "word": "తోఁటలను",
     "meaning": "తోటలలోని"
    },
    {
     "word": "బూవులు",
     "meaning": "పూలను"
    },
    {
     "word": "మ్రుచ్చిలి",
     "meaning": "దొంగిలించి"
    },
    {
     "word": "కోసి తెచ్చి",
     "meaning": "కోసుకొచ్చి"
    },
    {
     "word": "నా శిరమునఁ బోసినంతటనె",
     "meaning": "దేవుడనైన నా తలపై వేసినంత మాత్రాన"
    },
    {
     "word": "చేసిన పాపములు",
     "meaning": "చేసిన పాపాలు"
    },
    {
     "word": "ఒక్కసారిగా",
     "meaning": "వెంటనే"
    },
    {
     "word": "మఱచెడునట్టి",
     "meaning": "మరిచిపోతాయని భావించే"
    },
    {
     "word": "వెంగలినె",
     "meaning": "పిచ్చివాడివే"
    },
    {
     "word": "మానక",
     "meaning": "మానకుండా"
    },
    {
     "word": "ఇట్టివి",
     "meaning": "ఇలాంటి పనులు"
    }
   ],
   "bhavam": "ఓ దుర్మార్గుడా! రోజంతా తప్పు పనులు చేసి, సాయంత్రం వేళ పక్కవారి తోటలో పూలను దొంగిలించి తెచ్చి, దేవుడైన నా తలపై వేసినంత మాత్రాన నీ పాపాలన్నీ తొలగిపోతాయని అనుకోవడం నీ అమాయకత్వం లేదా పిచ్చితనం. దేవుని పూజ పేరుతో చేసే ఇటువంటి అకృత్యాలు ఎప్పటికీ పాపాన్ని పోగొట్టవు.",
   "word_count": 20,
   "gana_count": null,
   "line_count": 4,
   "poet_id": 23,
   "poet_name": "త్రిపురనేని రామస్వామి",
   "meter_id": 9,
   "meter_name": "చంపకమాల"
  },
  {
   "id": 2544,
   "title": "ధూర్తమానవా శతకము - 24",
   "text": "పసులను, జెట్టుచేమలను,-బక్షితతిన్‌, గ్రిమికీటకాదులన్‌\nబుసుకున దాకినంతఁ దల-పోయవు స్నానముమాట; కాని మా\nనిసి నినుఁ దాకినంతఁ దల-నిండుగ స్నానము ధర్మమార్గమే!\nముసిముసినవ్వు నవ్వెదవు-మోరెగబట్టుక ధూర్తమానవా!",
   "literary_form": "శతకం",
   "source": "ధూర్తమానవా శతకము",
   "kanda": null,
   "flags": null,
   "rating": "gold",
   "prathipadartham": [
    {
     "word": "పసులను",
     "meaning": "ఆవులను"
    },
    {
     "word": "జెట్టుచేమలను",
     "meaning": "అడవి మొక్కలను"
    },
    {
     "word": "బక్షితతిన్‌",
     "meaning": "పక్షుల సమూహాలను"
    },
    {
     "word": "గ్రిమికీటకాదులన్‌",
     "meaning": "పురుగులు మరియు కీటకాలను"
    },
    {
     "word": "బుసుకున",
     "meaning": "వేగంగా/అకస్మాత్తుగా"
    },
    {
     "word": "దాకినంతఁ",
     "meaning": "స్పర్శించినా"
    },
    {
     "word": "తలపోయవు",
     "meaning": "ఆలోచించవు"
    },
    {
     "word": "స్నానముమాట",
     "meaning": "స్నానం చేయాలనే విషయాన్ని"
    },
    {
     "word": "కాని",
     "meaning": "కానీ"
    },
    {
     "word": "మానిసి",
     "meaning": "మనుష్యుడు"
    },
    {
     "word": "నినుఁ",
     "meaning": "నిన్ను"
    },
    {
     "word": "దాకినంతఁ",
     "meaning": "స్పర్శిస్తే"
    },
    {
     "word": "తలనిండుగ",
     "meaning": "తలారా"
    },
    {
     "word": "స్నానము",
     "meaning": "స్నానం చేయడం"
    },
    {
     "word": "ధర్మమార్గమే",
     "meaning": "ధర్మమని భావిస్తావా"
    },
    {
     "word": "ముసిముసినవ్వు",
     "meaning": "చిరునవ్వు"
    },
    {
     "word": "నవ్వెదవు",
     "meaning": "నవ్వుతున్నావు"
    },
    {
     "word": "మోరెగబట్టుక",
     "meaning": "ముఖం ఎత్తి (గర్వంగా)"
    },
    {
     "word": "ధూర్తమానవా",
     "meaning": "దుర్మార్గుడైన మనిషి"
    }
   ],
   "bhavam": "ఓ ధూర్తమానవా! ఆవులను, పక్షులను, కీటకాలను తాకినప్పుడు స్నానం చేయాలనే ఆలోచన నీకు రాదు. కానీ, తోటి మనిషిని తాకితే మాత్రం స్నానం చేయడం ధర్మమని భావిస్తావు. నీ ఈ ద్వంద్వ వైఖరిని చూసి, నీవు గర్వంగా ముసిముసి నవ్వులు నవ్వుతున్నావు, ఇది నీ అజ్ఞానానికి నిదర్శనం.",
   "word_count": 18,
   "gana_count": null,
   "line_count": 4,
   "poet_id": 23,
   "poet_name": "త్రిపురనేని రామస్వామి",
   "meter_id": 9,
   "meter_name": "చంపకమాల"
  },
  {
   "id": 2545,
   "title": "ధూర్తమానవా శతకము - 25",
   "text": "బొచ్చు నొసంగి యెట్లు పరి-పూర్ణమనోరథసిద్ధిఁ బొందగా\nవచ్చును? బిచ్చివాఁడనని-భావమునం దలపోయుచుంటివా?\nపుచ్చును నీదు పాపములు-పోరచి మానుము యిట్టి వానినిన్‌;\nబొచ్చెము లిట్లుచెప్పి ప్రజ-మోసము చేయకు ధూర్తమానవా!",
   "literary_form": "శతకం",
   "source": "ధూర్తమానవా శతకము",
   "kanda": null,
   "flags": null,
   "rating": "gold",
   "prathipadartham": [
    {
     "word": "బొచ్చు",
     "meaning": "పిచ్చికూతలు లేదా వ్యర్థమైన మాటలు"
    },
    {
     "word": "ఒసంగి",
     "meaning": "ఇచ్చి"
    },
    {
     "word": "ఎట్లు",
     "meaning": "ఏ విధంగా"
    },
    {
     "word": "పరిపూర్ణ",
     "meaning": "సంపూర్ణమైన"
    },
    {
     "word": "మనోరథ",
     "meaning": "కోరికల"
    },
    {
     "word": "సిద్ధిన్",
     "meaning": "నెరవేర్పును"
    },
    {
     "word": "పొందగావచ్చును",
     "meaning": "పొందగలము"
    },
    {
     "word": "బిచ్చివాఁడను",
     "meaning": "నేను పిచ్చివాడినని"
    },
    {
     "word": "అని",
     "meaning": "అని"
    },
    {
     "word": "భావమునన్",
     "meaning": "మనస్సులో"
    },
    {
     "word": "తలపోయుచుంటివా",
     "meaning": "అనుకుంటున్నావా"
    },
    {
     "word": "పుచ్చును",
     "meaning": "నశింపజేస్తాయి"
    },
    {
     "word": "నీదు",
     "meaning": "నీ యొక్క"
    },
    {
     "word": "పాపములు",
     "meaning": "పాపాలు"
    },
    {
     "word": "పోరచి",
     "meaning": "కారణంగా"
    },
    {
     "word": "మానుము",
     "meaning": "వదిలిపెట్టు"
    },
    {
     "word": "ఇట్టివానినిన్",
     "meaning": "ఇలాంటి పనులను"
    },
    {
     "word": "బొచ్చెములు",
     "meaning": "బూటకపు మాటలు"
    },
    {
     "word": "ఇట్లుచెప్పి",
     "meaning": "ఇలా పలికి"
    },
    {
     "word": "ప్రజన్",
     "meaning": "ప్రజలను"
    },
    {
     "word": "మోసముచేయకు",
     "meaning": "వంచించకు"
    },
    {
     "word": "ధూర్తమానవా",
     "meaning": "దుర్మార్గుడా"
    }
   ],
   "bhavam": "ఓ దుర్మార్గుడా! ఇటువంటి అర్థం లేని మాటలు చెబుతూ, ప్రజలను ఎలా మోసం చేస్తావు? ఇటువంటి వ్యర్థమైన మాటల వల్ల కోరికలు నెరవేరవు. నన్ను పిచ్చివాడని భావించి ఇలా మోసం చేయాలని చూస్తున్నావా? ఇటువంటి అబద్ధాలు చెప్పడం వల్ల నీ పాపాలే పెరుగుతాయి, కాబట్టి ఇప్పటికైనా ఇట్టి పనులను మానివేయి.",
   "word_count": 19,
   "gana_count": null,
   "line_count": 4,
   "poet_id": 23,
   "poet_name": "త్రిపురనేని రామస్వామి",
   "meter_id": 8,
   "meter_name": "ఉత్పలమాల"
  },
  {
   "id": 2546,
   "title": "ధూర్తమానవా శతకము - 26",
   "text": "ఒక దేవాలయమందు స్త్రీలకు రహ-స్యోత్సాహివై బోధముల్‌\nనికరాదాయముతోడ జోడుచెవులున్‌-నిండించుచున్నావఁటే!\nఅకటా కొంపల నెన్ని దీసితివొ య-త్యాచారముల్‌ సల్పి, నీ\nమొకమున్‌ రాసెద మానకున్న యెడలన్‌-ముమ్మాటికిన్‌ ధూర్తమానవా!",
   "literary_form": "శతకం",
   "source": "ధూర్తమానవా శతకము",
   "kanda": null,
   "flags": null,
   "rating": null,
   "prathipadartham": [
    {
     "word": "ఒక",
     "meaning": "ఒక"
    },
    {
     "word": "దేవాలయమందు",
     "meaning": "గుడిలో"
    },
    {
     "word": "స్త్రీలకు",
     "meaning": "ఆడవారికి"
    },
    {
     "word": "రహస్య",
     "meaning": "దాపరికపు"
    },
    {
     "word": "ఉత్సాహివై",
     "meaning": "ఆసక్తి గలవాడవై"
    },
    {
     "word": "బోధముల్‌",
     "meaning": "ఉపదేశాలను"
    },
    {
     "word": "నికరాదాయముతోడ",
     "meaning": "ఖచ్చితమైన సంపాదనతో"
    },
    {
     "word": "జోడుచెవులున్‌",
     "meaning": "రెండు చెవులను"
    },
    {
     "word": "నిండించుచున్నావఁటే",
     "meaning": "నింపుతున్నావా"
    },
    {
     "word": "అకటా",
     "meaning": "అయ్యో"
    },
    {
     "word": "కొంపల",
     "meaning": "కాపురాలను"
    },
    {
     "word": "ఎన్ని",
     "meaning": "ఎన్నింటిని"
    },
    {
     "word": "దీసితివొ",
     "meaning": "పాడుచేశావో"
    },
    {
     "word": "అత్యాచారముల్‌",
     "meaning": "దుర్మార్గపు పనులను"
    },
    {
     "word": "సల్పి",
     "meaning": "చేసి"
    },
    {
     "word": "నీ",
     "meaning": "నీ"
    },
    {
     "word": "మొకమున్‌",
     "meaning": "ముఖాన్ని"
    },
    {
     "word": "రాసెద",
     "meaning": "మసిపూసి రాస్తాను"
    },
    {
     "word": "మానకున్న",
     "meaning": "మానుకోకపోతే"
    },
    {
     "word": "యెడలన్‌",
     "meaning": "ఒకవేళ"
    },
    {
     "word": "ముమ్మాటికిన్‌",
     "meaning": "నిశ్చయంగా"
    },
    {
     "word": "ధూర్తమానవా",
     "meaning": "దుర్మార్గుడా"
    }
   ],
   "bhavam": "ఓ దుర్మార్గుడా! నువ్వు ఒక దేవాలయంలో స్త్రీలకు రహస్యంగా బోధనలు చేస్తూ, డబ్బు సంపాదించుకుంటూ వారి చెవుల్లో విషాన్ని నింపుతున్నావా? ఇలాంటి అత్యాచారాలు చేస్తూ ఎన్ని కుటుంబాలను నాశనం చేశావో కదా! నీ ప్రవర్తన మార్చుకోకపోతే, నీ ముఖానికి మసి పూసి ఊరేగిస్తానని హెచ్చరిస్తున్నాను.",
   "word_count": 19,
   "gana_count": null,
   "line_count": 4,
   "poet_id": 23,
   "poet_name": "త్రిపురనేని రామస్వామి",
   "meter_id": 3,
   "meter_name": "Unknown"
  },
  {
   "id": 2547,
   "title": "ధూర్తమానవా శతకము - 27",
   "text": "బిడ్డలకోసరమ్ము విల-పించెడి యా జవరాండ్రతోడుతన్‌\nబిడ్డలు తప్పకుండఁ బ్రభ-వించెదరంచు సమాదరంబునన్‌\nగడ్డముపట్టి \"గర్భగుడి\"-గర్భముఁ జేర్చుదువట్టెరేల నో\nవెడ్డరి! నాకు మంచి పని-వెట్టితి వింతకు ధూర్తమానవా!",
   "literary_form": "శతకం",
   "source": "ధూర్తమానవా శతకము",
   "kanda": null,
   "flags": null,
   "rating": "gold",
   "prathipadartham": [
    {
     "word": "బిడ్డలకోసరమ్ము",
     "meaning": "పిల్లల కోసం"
    },
    {
     "word": "విలపించెడి",
     "meaning": "ఏడ్చుచున్న"
    },
    {
     "word": "యా",
     "meaning": "ఆ"
    },
    {
     "word": "జవరాండ్రతోడుతన్‌",
     "meaning": "స్త్రీలతో"
    },
    {
     "word": "బిడ్డలు",
     "meaning": "పిల్లలు"
    },
    {
     "word": "తప్పకుండన్‌",
     "meaning": "తప్పకుండా"
    },
    {
     "word": "ప్రభవించెదరు",
     "meaning": "పుడతారు"
    },
    {
     "word": "అంచు",
     "meaning": "అని చెప్పి"
    },
    {
     "word": "సమాదరంబునన్‌",
     "meaning": "గొప్ప గౌరవంతో / నమ్మకంతో"
    },
    {
     "word": "గడ్డముపట్టి",
     "meaning": "గడ్డం పట్టుకుని (వేడుకుంటూ)"
    },
    {
     "word": "గర్భగుడి",
     "meaning": "దేవాలయ గర్భాలయం"
    },
    {
     "word": "గర్భమున్‌",
     "meaning": "పొట్టను / గర్భాన్ని"
    },
    {
     "word": "జేర్చుదువు",
     "meaning": "చేర్చుతున్నావు"
    },
    {
     "word": "అట్టే",
     "meaning": "అలాగే"
    },
    {
     "word": "ఏల",
     "meaning": "ఎందుకు"
    },
    {
     "word": "ఓ",
     "meaning": "ఓ"
    },
    {
     "word": "వెడ్డరి",
     "meaning": "పిచ్చివాడా"
    },
    {
     "word": "నాకు",
     "meaning": "నాకు"
    },
    {
     "word": "మంచి పని",
     "meaning": "మంచి పనిని"
    },
    {
     "word": "వెట్టితి",
     "meaning": "అప్పగించావు (చాకిరీ చేయించావు)"
    },
    {
     "word": "ఇంతకు",
     "meaning": "ఇంతటి"
    },
    {
     "word": "ధూర్తమానవా",
     "meaning": "దుర్మార్గుడవైన మానవుడా"
    }
   ],
   "bhavam": "ఓ మూర్ఖుడవైన మానవుడా! పిల్లలు పుట్టడం లేదని ఏడ్చే స్త్రీలకు, గుడిలోని దేవుని గర్భాలయంలో దణ్ణం పెట్టుకుంటే కచ్చితంగా పిల్లలు పుడతారని నమ్మబలికి, వారిచేత గడ్డం పట్టుకుని బతిమాలేలా చేసి, వారికి ఇటువంటి పనిని అప్పగించావేమిటి? ఇది ఎంతటి మోసం!",
   "word_count": 18,
   "gana_count": null,
   "line_count": 4,
   "poet_id": 23,
   "poet_name": "త్రిపురనేని రామస్వామి",
   "meter_id": 8,
   "meter_name": "ఉత్పలమాల"
  },
  {
   "id": 2548,
   "title": "ధూర్తమానవా శతకము - 28",
   "text": "వాజను మానకున్న నప-వాదులు; తప్పవు శృంగభంగముల్‌;\nరోజులు నీకుఁ జాల విసి-రో! జులుమింతకు మానకున్నచోఁ\nబాజివియౌదు వీవు నగు-బాటు ఘటిల్లును; నింక మీఁద నీ\nపోజును జూచి మోసపడి-పోవుట గల్గదు ధూర్తమానవా!",
   "literary_form": "శతకం",
   "source": "ధూర్తమానవా శతకము",
   "kanda": null,
   "flags": null,
   "rating": "gold",
   "prathipadartham": [
    {
     "word": "ధూర్తమానవా",
     "meaning": "దుర్మార్గుడవైన ఓ మానవుడా"
    },
    {
     "word": "వాజను",
     "meaning": "చెడ్డ మాటలను"
    },
    {
     "word": "మానకున్న",
     "meaning": "మానుకోకపోతే"
    },
    {
     "word": "అపవాదులు",
     "meaning": "నిందలు"
    },
    {
     "word": "తప్పవు",
     "meaning": "తప్పవు"
    },
    {
     "word": "శృంగభంగముల్‌",
     "meaning": "అపజయాలు లేదా అవమానాలు"
    },
    {
     "word": "రోజులు",
     "meaning": "కాలం"
    },
    {
     "word": "నీకు",
     "meaning": "నీకు"
    },
    {
     "word": "చాలవు",
     "meaning": "అనుకూలించవు"
    },
    {
     "word": "విరోజులు",
     "meaning": "ఎదురుదెబ్బలు తగిలే రోజులు"
    },
    {
     "word": "ఇంతకు",
     "meaning": "ఈ ప్రవర్తనకు"
    },
    {
     "word": "మానకున్నచో",
     "meaning": "మానుకోకపోతే"
    },
    {
     "word": "బాజివి",
     "meaning": "ఓడిపోయిన వాడివి"
    },
    {
     "word": "అవుదువు",
     "meaning": "అవుతావు"
    },
    {
     "word": "నీవు",
     "meaning": "నీవు"
    },
    {
     "word": "నగుబాటు",
     "meaning": "నవ్వులపాలవ్వడం"
    },
    {
     "word": "ఘటిల్లును",
     "meaning": "జరుగుతుంది"
    },
    {
     "word": "ఇంక మీఁద",
     "meaning": "ఇక ముందు"
    },
    {
     "word": "నీ పోజును",
     "meaning": "నీ వేషధారణను లేదా డాంబికాన్ని"
    },
    {
     "word": "చూచి",
     "meaning": "చూసి"
    },
    {
     "word": "మోసపడిపోవుట",
     "meaning": "మోసపోవడం"
    },
    {
     "word": "కల్గదు",
     "meaning": "జరగదు"
    }
   ],
   "bhavam": "ఓ దుర్మార్గపు మనిషీ! నీవు ఇప్పటికైనా నీ చెడు ప్రవర్తనను, దుర్భాషలను మానుకోకపోతే ఖచ్చితంగా నిందలు, అవమానాలు ఎదుర్కోవాల్సి వస్తుంది. నీకు కాలం కలిసి రాదు. ఇలాగే కొనసాగితే నీవు అపజయాన్ని పొంది నలుగురిలో నవ్వులపాలవుతావు. ఇక ముందు నీ డాంబికమైన వేషధారణను చూసి ఎవరూ మోసపోరు.",
   "word_count": 23,
   "gana_count": null,
   "line_count": 4,
   "poet_id": 23,
   "poet_name": "త్రిపురనేని రామస్వామి",
   "meter_id": 8,
   "meter_name": "ఉత్పలమాల"
  },
  {
   "id": 2549,
   "title": "ధూర్తమానవా శతకము - 29",
   "text": "తిరిపెము నెత్తియెత్తి యతి-దీనతఁ దిర్గుచు జోలి బట్టుచున్‌\nతిరుపతికొండ మీఁది కెగ-దేకుచు నచ్చట చెప్పుదెబ్బ లీ\nవొరువుగఁ దిన్న లేశము ప్ర-యోజన ముండదు ధర్మమార్గమున్‌\nబిఱిఁదికిఁ ద్రోసిపుచ్చి పర-పీడకుఁ బూనిన ధూర్తమానవా!",
   "literary_form": "శతకం",
   "source": "ధూర్తమానవా శతకము",
   "kanda": null,
   "flags": null,
   "rating": "gold",
   "prathipadartham": [
    {
     "word": "ధూర్తమానవా",
     "meaning": "దుర్మార్గుడవైన ఓ మానవుడా"
    },
    {
     "word": "తిరిపెము",
     "meaning": "భిక్షను"
    },
    {
     "word": "ఎత్తి ఎత్తి",
     "meaning": "పదేపదే అడుగుతూ"
    },
    {
     "word": "అతి దీనతన్",
     "meaning": "మిక్కిలి దీనత్వంతో"
    },
    {
     "word": "తిరుగుచు",
     "meaning": "అటుఇటు తిరుగుతూ"
    },
    {
     "word": "జోలి పట్టుచున్",
     "meaning": "భిక్షా పాత్రను పట్టుకుని"
    },
    {
     "word": "తిరుపతి కొండ మీదికి",
     "meaning": "తిరుమల కొండపైకి"
    },
    {
     "word": "ఎగదేకుచు",
     "meaning": "కష్టపడుతూ ఎక్కుతూ"
    },
    {
     "word": "అచ్చట",
     "meaning": "అక్కడ"
    },
    {
     "word": "చెప్పు దెబ్బలు",
     "meaning": "చెప్పుల దెబ్బలను"
    },
    {
     "word": "ఈ వొరువుగ",
     "meaning": "ఇష్టపూర్వకంగా/ఓర్పుగా"
    },
    {
     "word": "తిన్న",
     "meaning": "అనుభవించినా"
    },
    {
     "word": "లేశము",
     "meaning": "కొంచెం కూడా"
    },
    {
     "word": "ప్రయోజనము ఉండదు",
     "meaning": "లాభం లేదు"
    },
    {
     "word": "ధర్మమార్గమున్",
     "meaning": "ధర్మ మార్గాన్ని"
    },
    {
     "word": "బిఱిదికి తోసిపుచ్చి",
     "meaning": "పక్కన పెట్టి/వదిలేసి"
    },
    {
     "word": "పరపీడకు",
     "meaning": "ఇతరులను బాధించడానికి"
    },
    {
     "word": "పూనిన",
     "meaning": "కడంగిన"
    }
   ],
   "bhavam": "ఓ దుర్మార్గుడా! ధర్మ మార్గాన్ని విడిచిపెట్టి ఇతరులను పీడించే నీవు, దైవ దర్శనం కోసం భిక్షా పాత్ర పట్టుకుని దీనంగా తిరుగుతూ, తిరుపతి కొండపైకి కష్టపడి ఎక్కి అక్కడ అవమానకరమైన చెప్పు దెబ్బలు తిన్నా సరే, దానివల్ల నీకు ఏమాత్రం ప్రయోజనం ఉండదు.",
   "word_count": 23,
   "gana_count": null,
   "line_count": 4,
   "poet_id": 23,
   "poet_name": "త్రిపురనేని రామస్వామి",
   "meter_id": 9,
   "meter_name": "చంపకమాల"
  },
  {
   "id": 2550,
   "title": "ధూర్తమానవా శతకము - 30",
   "text": "తిరుపతిఁ బుట్టి; రంగపురి-తెన్నుల వర్ధిలి; కాశిలోపలన్‌\nమరణము పొందినప్పటికి-మారదు కర్మఫలానుభూతి; నీ\nవెరిగియు దీని స్వార్థరతి-నెల్లవిధంబుల నెంతమందినో\nపురపుర నెల్లవేళలను-మోసముఁ జేతువే ధూర్తమానవా!",
   "literary_form": "శతకం",
   "source": "ధూర్తమానవా శతకము",
   "kanda": null,
   "flags": null,
   "rating": null,
   "prathipadartham": [
    {
     "word": "తిరుపతిఁ",
     "meaning": "తిరుపతిలో"
    },
    {
     "word": "బుట్టి",
     "meaning": "జన్మించి"
    },
    {
     "word": "రంగపురి-తెన్నుల",
     "meaning": "శ్రీరంగపట్నం మార్గాల్లో"
    },
    {
     "word": "వర్ధిలి",
     "meaning": "పెరిగి జీవించి"
    },
    {
     "word": "కాశిలోపలన్‌",
     "meaning": "కాశీ పట్టణంలో"
    },
    {
     "word": "మరణము",
     "meaning": "మరణాన్ని"
    },
    {
     "word": "పొందినప్పటికి",
     "meaning": "పొందినప్పటికీ"
    },
    {
     "word": "మారదు",
     "meaning": "తప్పదు/మార్పు ఉండదు"
    },
    {
     "word": "కర్మఫలానుభూతి",
     "meaning": "చేసిన పనుల యొక్క ఫలితాలను అనుభవించడం"
    },
    {
     "word": "నీవు",
     "meaning": "నీవు"
    },
    {
     "word": "ఎరిగియు",
     "meaning": "తెలిసి ఉండి కూడా"
    },
    {
     "word": "దీని",
     "meaning": "ఈ సత్యాన్ని"
    },
    {
     "word": "స్వార్థరతి",
     "meaning": "స్వార్థపూరితమైన ఆసక్తితో"
    },
    {
     "word": "నెల్లవిధంబుల",
     "meaning": "అన్ని రకాలుగా"
    },
    {
     "word": "నెంతమందినో",
     "meaning": "ఎంతో మంది అమాయకులను"
    },
    {
     "word": "పురపుర",
     "meaning": "బాధపడేలా/ఏడ్చేలా"
    },
    {
     "word": "నెల్లవేళలను",
     "meaning": "అన్ని సమయాల్లో"
    },
    {
     "word": "మోసముఁ జేతువే",
     "meaning": "ఎందుకు మోసం చేస్తున్నావు?"
    },
    {
     "word": "ధూర్తమానవా",
     "meaning": "ఓ దుర్మార్గుడా/దుష్ట మానవుడా"
    }
   ],
   "bhavam": "ఓ దుర్మార్గుడా! తిరుపతిలో జన్మించినా, శ్రీరంగంలో జీవించినా లేదా కాశీలో మరణించినా, మనిషి తాను చేసిన కర్మల ఫలితాన్ని అనుభవించక తప్పదు. ఈ సత్యం నీకు తెలిసినా, కేవలం నీ స్వార్థం కోసం ఎంతో మందిని నానా రకాలుగా బాధపెడుతూ, మోసం చేస్తూ ఎందుకు తిరుగుతున్నావు?",
   "word_count": 17,
   "gana_count": null,
   "line_count": 4,
   "poet_id": 23,
   "poet_name": "త్రిపురనేని రామస్వామి",
   "meter_id": 3,
   "meter_name": "Unknown"
  },
  {
   "id": 2551,
   "title": "ధూర్తమానవా శతకము - 31",
   "text": "ఇతరులఁ బర్వుతో బ్రదుక-నిచ్చుట నెన్నఁడు నేర్చికొందు వా\nయతమగు నీ ప్రపంచసుఖ-మన్నది యొక్కటె నీ సుఖంబుగాఁ\nబ్రతిదినమున్‌ స్మరించు సమ-భావము నెన్నఁడు నేర్చికొందు వు\nన్నతిఁ గనుచుండి నీ ప్రజ ల-నారతమున్‌ నినుమెచ్చ మానవా!",
   "literary_form": "శతకం",
   "source": "ధూర్తమానవా శతకము",
   "kanda": null,
   "flags": null,
   "rating": "gold",
   "prathipadartham": [
    {
     "word": "మానవా!",
     "meaning": "ఓ మానవుడా!"
    },
    {
     "word": "ఇతరులన్",
     "meaning": "అన్యులను (ఇతరులను)"
    },
    {
     "word": "పర్వుతో",
     "meaning": "గౌరవంతో/మర్యాదతో"
    },
    {
     "word": "బ్రదుకనిచ్చుట",
     "meaning": "జీవించడానికి అనుమతించడం"
    },
    {
     "word": "ఎన్నడు",
     "meaning": "ఎప్పుడు"
    },
    {
     "word": "నేర్చికొందువు?",
     "meaning": "నేర్చుకుంటావు?"
    },
    {
     "word": "అయతమగు",
     "meaning": "విశాలమైన/అతిశయమైన"
    },
    {
     "word": "ఈ ప్రపంచసుఖం",
     "meaning": "ఈ లోకంలోని సుఖం"
    },
    {
     "word": "అన్నది",
     "meaning": "అనేది"
    },
    {
     "word": "ఒక్కటె",
     "meaning": "ఒక్కటే"
    },
    {
     "word": "నీ సుఖంబుగా",
     "meaning": "నీ స్వంత సుఖంగా"
    },
    {
     "word": "ప్రతిదినమున్",
     "meaning": "ప్రతిరోజూ"
    },
    {
     "word": "స్మరించు",
     "meaning": "తలచే"
    },
    {
     "word": "సమభావము",
     "meaning": "సమాన దృక్పథాన్ని"
    },
    {
     "word": "ఎన్నడు",
     "meaning": "ఎప్పుడు"
    },
    {
     "word": "నేర్చికొందువు?",
     "meaning": "నేర్చుకుంటావు?"
    },
    {
     "word": "నీ ప్రజలు",
     "meaning": "నీ తోటి మనుషులు"
    },
    {
     "word": "ఉన్నతిని",
     "meaning": "అభివృద్ధిని/మేలును"
    },
    {
     "word": "కనుచుండి",
     "meaning": "చూస్తూ"
    },
    {
     "word": "అనారతమున్",
     "meaning": "ఎల్లప్పుడూ"
    },
    {
     "word": "నిను",
     "meaning": "నిన్ను"
    },
    {
     "word": "మెచ్చ",
     "meaning": "మెచ్చుకునేలా (ప్రశంసించేలా)"
    }
   ],
   "bhavam": "ఓ మానవుడా! ఇతరులను గౌరవంగా బ్రతకనివ్వడం ఎప్పుడు నేర్చుకుంటావు? ప్రపంచంలోని సుఖమే తన సుఖమని భావించే విశాల దృక్పథాన్ని ఎప్పుడు అలవర్చుకుంటావు? నీ తోటి మనుషులందరూ నిన్ను ఎల్లప్పుడూ గౌరవించేలా, నీ ప్రవర్తనను మెచ్చుకునేలా నువ్వు ఎప్పుడు ప్రవర్తిస్తావు?",
   "word_count": 25,
   "gana_count": null,
   "line_count": 4,
   "poet_id": 23,
   "poet_name": "త్రిపురనేని రామస్వామి",
   "meter_id": 9,
   "meter_name": "చంపకమాల"
  },
  {
   "id": 2552,
   "title": "ధూర్తమానవా శతకము - 32",
   "text": "చేసినవేమో చేసితివి-చెన్నటివై; యని నేను సైరణన్‌\nజేసితి; నింకముందయినఁ-జేసిన తప్పుల దిద్దుబాటుకై\nగాసిలియైన యత్నములు-గట్టిగఁ జేయక యూరకున్నచో\nవేసరఁబోక కట్టి కుడి-పించెదఁ తప్పదు ధూర్తమానవా!",
   "literary_form": "శతకం",
   "source": "ధూర్తమానవా శతకము",
   "kanda": null,
   "flags": null,
   "rating": null,
   "prathipadartham": [
    {
     "word": "చేసినవేమో",
     "meaning": "నీవు చేసిన పనులేవో"
    },
    {
     "word": "చేసితివి",
     "meaning": "చేసేసితివి"
    },
    {
     "word": "చెన్నటివై",
     "meaning": "అవి మంచివని తలచి"
    },
    {
     "word": "అని",
     "meaning": "అని భావించి"
    },
    {
     "word": "నేను",
     "meaning": "నేను"
    },
    {
     "word": "సైరణన్",
     "meaning": "ఓర్పుతో (సహనంతో)"
    },
    {
     "word": "జేసితి",
     "meaning": "భరించాను"
    },
    {
     "word": "ఇంకముందయినన్",
     "meaning": "ఇక ముందుకైనా"
    },
    {
     "word": "చేసిన",
     "meaning": "నువ్వు చేసిన"
    },
    {
     "word": "తప్పుల",
     "meaning": "తప్పులను"
    },
    {
     "word": "దిద్దుబాటుకై",
     "meaning": "సరిదిద్దుకోవడానికి"
    },
    {
     "word": "గాసిలియైన",
     "meaning": "కష్టపడియైనా"
    },
    {
     "word": "యత్నములు",
     "meaning": "ప్రయత్నాలను"
    },
    {
     "word": "గట్టిగన్",
     "meaning": "నిశ్చయంగా"
    },
    {
     "word": "జేయక",
     "meaning": "చేయకుండా"
    },
    {
     "word": "ఊరకున్నచో",
     "meaning": "నిమ్మకు నీరెత్తినట్లు ఊరుకుంటే"
    },
    {
     "word": "వేసరన్",
     "meaning": "అలసట చెందకుండా"
    },
    {
     "word": "పోక",
     "meaning": "వెళ్ళకుండా"
    },
    {
     "word": "కట్టి",
     "meaning": "బలంగా కట్టేసి"
    },
    {
     "word": "కుడిపించెదన్",
     "meaning": "తగిన శిక్షను అనుభవింపజేస్తాను"
    },
    {
     "word": "తప్పదు",
     "meaning": "ఇది ఖాయం"
    },
    {
     "word": "ధూర్తమానవా",
     "meaning": "దుర్మార్గపు మనిషీ!"
    }
   ],
   "bhavam": "ఓ దుర్మార్గపు మనిషీ! ఇప్పటివరకు నువ్వు చేసిన పనులను మంచివే అని భావించి నేను ఓర్పుతో భరించాను. కానీ ఇప్పటికైనా సరే, నువ్వు చేసిన తప్పులను సరిదిద్దుకోవడానికి కష్టపడి ప్రయత్నించాలి. అలా కాకుండా ఏ ప్రయత్నమూ చేయకుండా సోమరిగా ఉంటే, నిన్ను కట్టివేసి మరీ నీ తప్పులకు తగిన శిక్షను అనుభవింపజేస్తాను. ఇది ఖాయం.",
   "word_count": 18,
   "gana_count": null,
   "line_count": 4,
   "poet_id": 23,
   "poet_name": "త్రిపురనేని రామస్వామి",
   "meter_id": 3,
   "meter_name": "Unknown"
  },
  {
   "id": 2553,
   "title": "ధూర్తమానవా శతకము - 33",
   "text": "నే వచ్చి నీకుఁ గలలో\nవావిరి చెప్పినది యెల్ల వ్రాయుటచేతన్‌\nనీవే ధన్యుఁడ వైతివి\nరావోయీ! త్రిపురనేని రామస్వామీ!",
   "literary_form": "శతకం",
   "source": "ధూర్తమానవా శతకము",
   "kanda": null,
   "flags": null,
   "rating": "gold",
   "prathipadartham": [
    {
     "word": "నే",
     "meaning": "నేను"
    },
    {
     "word": "వచ్చి",
     "meaning": "వచ్చి"
    },
    {
     "word": "నీకున్‌",
     "meaning": "నీకు"
    },
    {
     "word": "కలలో",
     "meaning": "కలయందు"
    },
    {
     "word": "వావిరి",
     "meaning": "క్రమముగా"
    },
    {
     "word": "చెప్పినది",
     "meaning": "చెప్పిన విషయాలన్నీ"
    },
    {
     "word": "ఎల్ల",
     "meaning": "సమస్తము"
    },
    {
     "word": "వ్రాయుటచేతన్‌",
     "meaning": "రాసిపెట్టడం వల్ల"
    },
    {
     "word": "నీవే",
     "meaning": "నీవే"
    },
    {
     "word": "ధన్యుఁడవు",
     "meaning": "కృతార్థుడవు"
    },
    {
     "word": "అయితివి",
     "meaning": "అయ్యావు"
    },
    {
     "word": "రావోయీ",
     "meaning": "ఓయి రా స్వామి"
    },
    {
     "word": "త్రిపురనేని",
     "meaning": "త్రిపురనేని వంశజుడా"
    },
    {
     "word": "రామస్వామీ",
     "meaning": "రామస్వామి"
    }
   ],
   "bhavam": "నేను కలలో నీకు క్రమంగా చెప్పిన విషయాలన్నింటినీ నీవు రాసిపెట్టినందువల్ల నీవు ధన్యుడవైతివి, ఓ త్రిపురనేని రామస్వామీ! రావోయి.",
   "word_count": 14,
   "gana_count": null,
   "line_count": 4,
   "poet_id": 23,
   "poet_name": "త్రిపురనేని రామస్వామి",
   "meter_id": 41,
   "meter_name": "కందము"
  },
  {
   "id": 2554,
   "title": "ధూర్తమానవా శతకము - 34",
   "text": "పైగా నాతనినే విమానముపయిన్‌-స్వర్గంబు గొంపోయి త\nద్భోగావాప్తిని గూర్చినాఁడ నని సు-ద్దుల్‌ చెప్పుచున్నాఁడవా?\nజాగీరిచ్చునె యే ప్రభుండయిన రా-జద్రోహికిన్‌ స్వర్గమా?\nనీ గాండ్రింపులు గట్టిపెట్ట నిఁకనే-నిన్‌ బూనవా? మానవా!",
   "literary_form": "శతకం",
   "source": "ధూర్తమానవా శతకము",
   "kanda": null,
   "flags": null,
   "rating": "gold",
   "prathipadartham": [
    {
     "word": "పైగా",
     "meaning": "అంతేకాకుండా"
    },
    {
     "word": "నాతనినే",
     "meaning": "ఆ వ్యక్తిని"
    },
    {
     "word": "విమానముపయిన్",
     "meaning": "విమానం మీద కూర్చోబెట్టి"
    },
    {
     "word": "స్వర్గంబు",
     "meaning": "స్వర్గలోకానికి"
    },
    {
     "word": "గొంపోయి",
     "meaning": "తీసుకెళ్లి"
    },
    {
     "word": "తద్భోగావాప్తిని",
     "meaning": "అక్కడ ఉండే భోగ భాగ్యాలను పొందేలా"
    },
    {
     "word": "గూర్చినాడను",
     "meaning": "కల్పించాను అని"
    },
    {
     "word": "అని",
     "meaning": "అని"
    },
    {
     "word": "సుద్దుల్",
     "meaning": "కబుర్లు / గొప్పలు"
    },
    {
     "word": "చెప్పుచున్నాడవా",
     "meaning": "చెబుతున్నావా"
    },
    {
     "word": "జాగీరిచ్చునె",
     "meaning": "బహుమతిని ఇస్తారా"
    },
    {
     "word": "ఏ ప్రభుండయిన",
     "meaning": "ఎటువంటి రాజు అయినా"
    },
    {
     "word": "రాజద్రోహికిన్",
     "meaning": "రాజద్రోహం చేసిన వాడికి"
    },
    {
     "word": "స్వర్గమా",
     "meaning": "స్వర్గం (బహుమానం) ఇస్తారా"
    },
    {
     "word": "నీ",
     "meaning": "నీ యొక్క"
    },
    {
     "word": "గాండ్రింపులు",
     "meaning": "అరుపులు/బూటకపు మాటలు"
    },
    {
     "word": "గట్టిపెట్ట",
     "meaning": "ఆపివేయడానికి"
    },
    {
     "word": "ఇకనేనిన్",
     "meaning": "ఇప్పటికైనా"
    },
    {
     "word": "బూనవా",
     "meaning": "ప్రయత్నించవా"
    },
    {
     "word": "మానవా",
     "meaning": "ఓ మనిషీ"
    }
   ],
   "bhavam": "ఓ మనిషీ! చనిపోయిన వ్యక్తిని విమానంలో స్వర్గానికి తీసుకెళ్లి, అక్కడ అతనికి సుఖభోగాలు కల్పించానని నువ్వు గొప్పలు చెప్పుకుంటున్నావా? రాజద్రోహం చేసిన వాడికి ఏ రాజైనా బహుమతి ఇస్తాడా? నీ ఈ బూటకపు మాటలను, అరుపులను ఇకనైనా ఆపే ప్రయత్నం చేయవా?",
   "word_count": 21,
   "gana_count": null,
   "line_count": 4,
   "poet_id": 23,
   "poet_name": "త్రిపురనేని రామస్వామి",
   "meter_id": 6,
   "meter_name": "శార్దూలవిక్రీడితము"
  },
  {
   "id": 2555,
   "title": "ధూర్తమానవా శతకము - 35",
   "text": "ఎడ్డెతనంబుఁ జూపెదవె!-యెంతని నే సహియింతు నిన్ను; నీ\nకడ్డము వచ్చినంతటనె-యాతఁడు ధర్మవిదూరుడౌనె? పెన్‌\nగడ్డము లేకయున్న నెటు-కాఁగలడయ్య ఋషీంద్రుఁ డెందు! నీ\nనడ్డి విఱుంగు నింకపయి-నన్‌ మతిదప్పిన ధూర్తమానవా!",
   "literary_form": "శతకం",
   "source": "ధూర్తమానవా శతకము",
   "kanda": null,
   "flags": null,
   "rating": "gold",
   "prathipadartham": [
    {
     "word": "ఎడ్డెతనంబు",
     "meaning": "మూర్ఖత్వాన్ని"
    },
    {
     "word": "చూపెదవె",
     "meaning": "ప్రదర్శిస్తున్నావా"
    },
    {
     "word": "ఎంతని",
     "meaning": "ఎంతవరకు"
    },
    {
     "word": "నే",
     "meaning": "నేను"
    },
    {
     "word": "సహియింతు",
     "meaning": "భరిస్తాను"
    },
    {
     "word": "నిన్ను",
     "meaning": "నిన్ను"
    },
    {
     "word": "నీకు",
     "meaning": "నీకు"
    },
    {
     "word": "అడ్డము",
     "meaning": "ఎదురుగా"
    },
    {
     "word": "వచ్చినంతటనె",
     "meaning": "రాగానే"
    },
    {
     "word": "అతడు",
     "meaning": "అతడు"
    },
    {
     "word": "ధర్మవిదూరుడు",
     "meaning": "ధర్మానికి దూరమైనవాడు"
    },
    {
     "word": "అవునే",
     "meaning": "అవుతాడా"
    },
    {
     "word": "పెన్ గడ్డము",
     "meaning": "పెద్ద గడ్డం"
    },
    {
     "word": "లేకయున్న",
     "meaning": "లేకపోతే"
    },
    {
     "word": "ఎటు",
     "meaning": "ఎలా"
    },
    {
     "word": "కాగలడయ్య",
     "meaning": "అవ్వగలడు"
    },
    {
     "word": "ఋషీంద్రుడు",
     "meaning": "మహాఋషి"
    },
    {
     "word": "ఎందు",
     "meaning": "ఎక్కడైనా"
    },
    {
     "word": "నీ",
     "meaning": "నీ"
    },
    {
     "word": "నడ్డి",
     "meaning": "వెన్నుముక"
    },
    {
     "word": "విఱుంగు",
     "meaning": "విరుగుతుంది"
    },
    {
     "word": "ఇంకపయి",
     "meaning": "ఇకమీదట"
    },
    {
     "word": "అన్",
     "meaning": "నన్ను"
    },
    {
     "word": "మతితప్పిన",
     "meaning": "బుద్ధిహీనుడైన"
    },
    {
     "word": "ధూర్తమానవా",
     "meaning": "దుర్మార్గుడా"
    }
   ],
   "bhavam": "ఓ బుద్ధిహీనుడవైన దుర్మార్గుడా! నీ మూర్ఖత్వాన్ని ఇంకెన్నాళ్ళు ప్రదర్శిస్తావు? నీకు నచ్చకపోగానే ఎదుటివాడు ధర్మహీనుడు అవుతాడా? గడ్డం ఉంటేనే ఋషి అనడం ఎంత అర్థరహితం? ఇలాంటి పిచ్చి వాదనలు ఆపకపోతే నీకు తగిన శాస్తి జరుగుతుంది, జాగ్రత్త.",
   "word_count": 21,
   "gana_count": null,
   "line_count": 4,
   "poet_id": 23,
   "poet_name": "త్రిపురనేని రామస్వామి",
   "meter_id": 8,
   "meter_name": "ఉత్పలమాల"
  },
  {
   "id": 2556,
   "title": "ధూర్తమానవా శతకము - 36",
   "text": "ఆ యాచార్యుఁ డెవఁడో తెల్పవుగ య-త్యాచారముం జల్పుచున్‌\nకాయంబెల్లను రాజయక్ష్మయను రో-గంబందుటన్‌ గ్రుళ్ళి వే\nయాయాసంబునఁ దూలుచున్నతఁడు నా-యాచార్యులం దొక్కఁడా?\nనాయాజ్ఞా పరిపాలురం దొకఁడ! నన్‌-వంచింతువా? మానవా!",
   "literary_form": "శతకం",
   "source": "ధూర్తమానవా శతకము",
   "kanda": null,
   "flags": null,
   "rating": null,
   "prathipadartham": [
    {
     "word": "ఆ యాచార్యుఁడు",
     "meaning": "ఆ గురువు ఎవరో"
    },
    {
     "word": "ఎవఁడో",
     "meaning": "ఎవరో"
    },
    {
     "word": "తెల్పవుగ",
     "meaning": "చెప్పవు కదా"
    },
    {
     "word": "యత్యాచారముం",
     "meaning": "దురాచారమును"
    },
    {
     "word": "జల్పుచున్‌",
     "meaning": "చేయుచు"
    },
    {
     "word": "కాయంబెల్లను",
     "meaning": "శరీరమంతయు"
    },
    {
     "word": "రాజయక్ష్మ",
     "meaning": "క్షయ వ్యాధి"
    },
    {
     "word": "అను",
     "meaning": "అనే"
    },
    {
     "word": "రోగం",
     "meaning": "జబ్బు"
    },
    {
     "word": "అందుటన్‌",
     "meaning": "పొందడం వల్ల"
    },
    {
     "word": "గ్రుళ్ళి",
     "meaning": "కుళ్ళిపోతూ"
    },
    {
     "word": "వే",
     "meaning": "అత్యంత"
    },
    {
     "word": "ఆయాసంబునన్‌",
     "meaning": "అలసటతో"
    },
    {
     "word": "తూలుచున్నతఁడు",
     "meaning": "తూలిపోతున్నవాడు"
    },
    {
     "word": "నా ఆచార్యులందు",
     "meaning": "నా గురువులలో"
    },
    {
     "word": "ఒక్కఁడా?",
     "meaning": "ఒకడా?"
    },
    {
     "word": "నా ఆజ్ఞా పరిపాలురందు",
     "meaning": "నా ఆజ్ఞలను పాలించే వారిలో"
    },
    {
     "word": "ఒకఁడా?",
     "meaning": "ఒకడా?"
    },
    {
     "word": "నన్‌",
     "meaning": "నన్ను"
    },
    {
     "word": "వంచింతువా?",
     "meaning": "మోసగిస్తావా?"
    },
    {
     "word": "మానవా!",
     "meaning": "ఓ మానవుడా!"
    }
   ],
   "bhavam": "ఓ మానవుడా! నీవు చెబుతున్న ఆ ఆచార్యుడు ఎవరో నాకు తెలియదు. దురాచారాలకు పాల్పడుతూ, క్షయవ్యాధితో శరీరం కుళ్ళిపోయి, అలసటతో తూలిపోతున్న ఆ వ్యక్తి నా గురువులలో ఒకడా? లేదా నా ఆజ్ఞలను పాటించే వారిలో ఒకడా? ఇలాంటి వాడిని ఆచార్యుడు అని చెప్పి నన్ను మోసం చేస్తున్నావా?",
   "word_count": 20,
   "gana_count": null,
   "line_count": 4,
   "poet_id": 23,
   "poet_name": "త్రిపురనేని రామస్వామి",
   "meter_id": 3,
   "meter_name": "Unknown"
  }
 ]
}